Workbook

Sheet 8月成交数据
A1: 日期 | B1: 业务组 | C1: 战区 | D1: 城市 | E1: 小组 | F1: 成交额 | G1: 应收利息 | H1: 逾期金额 | I1: 战区编号 | J1: 战区经理 | K1: 战区等级 | L1: 城市编号 | M1: 城市经理 | N1: 城市等级 | O1: 平均月薪 | P1: 注册人数 | Q1: 实名认证人数 | R1: 戳额人数 | S1: 给额人数 | T1: 成交人数 | U1: 平均芝麻分
A2: 44044 | B2: 西部战区-重庆-重庆一组 | C2: 西部战区 | D2: 重庆 | E2: 重庆一组 | F2: 15568 | G2: 1009 | H2: 0 | I2: =_xlfn.XLOOKUP($C2,战区信息!$A$1:$A$5,战区信息!$B$1:$B$5) -> 003 | J2: =_xlfn.XLOOKUP($C2,战区信息!$A$1:$A$5,战区信息!$C$1:$C$5) -> 田楠 | K2: =_xlfn.XLOOKUP($C2,战区信息!$A$1:$A$5,战区信息!$D$1:$D$5) -> 二级战区 | L2: =_xlfn.XLOOKUP($D2,城市信息!$B$1:$B$14,城市信息!$A$1:$A$14) -> 012 | M2: =_xlfn.XLOOKUP($D2,城市信息!$B$1:$B$14,城市信息!$C$1:$C$14) -> 于子默 | N2: =_xlfn.XLOOKUP($D2,城市信息!$B$1:$B$14,城市信息!$D$1:$D$14) -> 二线 | O2: =_xlfn.XLOOKUP($D2,城市信息!$B$1:$B$14,城市信息!$E$1:$E$14) -> 9713 | P2: {=_xlfn.XLOOKUP(A2&B2,'[1]2.4自动化报表-8月获客数据-非乱码'!$A:$A&'[1]2.4自动化报表-8月获客数据-非乱码'!$B:$B,'[1]2.4自动化报表-8月获客数据-非乱码'!$C:$H)} -> 1387 | Q2: 1375 | R2: 1327 | S2: 836 | T2: 439 | U2: 688
A3: 44044 | B3: 西部战区-西安-西安一组 | C3: 西部战区 | D3: 西安 | E3: 西安一组 | F3: 53172 | G3: 4791 | H3: 0 | I3: =_xlfn.XLOOKUP($C3,战区信息!$A$1:$A$5,战区信息!$B$1:$B$5) -> 003 | J3: =_xlfn.XLOOKUP($C3,战区信息!$A$1:$A$5,战区信息!$C$1:$C$5) -> 田楠 | K3: =_xlfn.XLOOKUP($C3,战区信息!$A$1:$A$5,战区信息!$D$1:$D$5) -> 二级战区 | L3: =_xlfn.XLOOKUP($D3,城市信息!$B$1:$B$14,城市信息!$A$1:$A$14) -> 010 | M3: =_xlfn.XLOOKUP($D3,城市信息!$B$1:$B$14,城市信息!$C$1:$C$14) -> 黄鹏天 | N3: =_xlfn.XLOOKUP($D3,城市信息!$B$1:$B$14,城市信息!$D$1:$D$14) -> 二线 | O3: =_xlfn.XLOOKUP($D3,城市信息!$B$1:$B$14,城市信息!$E$1:$E$14) -> 8295 | P3: {=_xlfn.XLOOKUP(A3&B3,'[1]2.4自动化报表-8月获客数据-非乱码'!$A:$A&'[1]2.4自动化报表-8月获客数据-非乱码'!$B:$B,'[1]2.4自动化报表-8月获客数据-非乱码'!$C:$H)} -> 3717 | Q3: 3652 | R3: 3534 | S3: 2135 | T3: 1196 | U3: 691
A4: 44044 | B4: 西部战区-武汉-武汉一组 | C4: 西部战区 | D4: 武汉 | E4: 武汉一组 | F4: 45255 | G4: 5447 | H4: 0 | I4: =_xlfn.XLOOKUP($C4,战区信息!$A$1:$A$5,战区信息!$B$1:$B$5) -> 003 | J4: =_xlfn.XLOOKUP($C4,战区信息!$A$1:$A$5,战区信息!$C$1:$C$5) -> 田楠 | K4: =_xlfn.XLOOKUP($C4,战区信息!$A$1:$A$5,战区信息!$D$1:$D$5) -> 二级战区 | L4: =_xlfn.XLOOKUP($D4,城市信息!$B$1:$B$14,城市信息!$A$1:$A$14) -> 006 | M4: =_xlfn.XLOOKUP($D4,城市信息!$B$1:$B$14,城市信息!$C$1:$C$14) -> 王刚 | N4: =_xlfn.XLOOKUP($D4,城市信息!$B$1:$B$14,城市信息!$D$1:$D$14) -> 二线 | O4: =_xlfn.XLOOKUP($D4,城市信息!$B$1:$B$14,城市信息!$E$1:$E$14) -> 9107 | P4: {=_xlfn.XLOOKUP(A4&B4,'[1]2.4自动化报表-8月获客数据-非乱码'!$A:$A&'[1]2.4自动化报表-8月获客数据-非乱码'!$B:$B,'[1]2.4自动化报表-8月获客数据-非乱码'!$C:$H)} -> 2052 | Q4: 1990 | R4: 1900 | S4: 1211 | T4: 553 | U4: 700
A5: 44044 | B5: 西部战区-成都-成都一组 | C5: 西部战区 | D5: 成都 | E5: 成都一组 | F5: 102755 | G5: 10027 | H5: 0 | I5: =_xlfn.XLOOKUP($C5,战区信息!$A$1:$A$5,战区信息!$B$1:$B$5) -> 003 | J5: =_xlfn.XLOOKUP($C5,战区信息!$A$1:$A$5,战区信息!$C$1:$C$5) -> 田楠 | K5: =_xlfn.XLOOKUP($C5,战区信息!$A$1:$A$5,战区信息!$D$1:$D$5) -> 二级战区 | L5: =_xlfn.XLOOKUP($D5,城市信息!$B$1:$B$14,城市信息!$A$1:$A$14) -> 009 | M5: =_xlfn.XLOOKUP($D5,城市信息!$B$1:$B$14,城市信息!$C$1:$C$14) -> 叶超 | N5: =_xlfn.XLOOKUP($D5,城市信息!$B$1:$B$14,城市信息!$D$1:$D$14) -> 二线 | O5: =_xlfn.XLOOKUP($D5,城市信息!$B$1:$B$14,城市信息!$E$1:$E$14) -> 9016 | P5: {=_xlfn.XLOOKUP(A5&B5,'[1]2.4自动化报表-8月获客数据-非乱码'!$A:$A&'[1]2.4自动化报表-8月获客数据-非乱码'!$B:$B,'[1]2.4自动化报表-8月获客数据-非乱码'!$C:$H)} -> 2179 | Q5: 2129 | R5: 2053 | S5: 1330 | T5: 782 | U5: 692
A6: 44044 | B6: 西部战区-成都-成都二组 | C6: 西部战区 | D6: 成都 | E6: 成都二组 | F6: 5500 | G6: 789 | H6: 0 | I6: =_xlfn.XLOOKUP($C6,战区信息!$A$1:$A$5,战区信息!$B$1:$B$5) -> 003 | J6: =_xlfn.XLOOKUP($C6,战区信息!$A$1:$A$5,战区信息!$C$1:$C$5) -> 田楠 | K6: =_xlfn.XLOOKUP($C6,战区信息!$A$1:$A$5,战区信息!$D$1:$D$5) -> 二级战区 | L6: =_xlfn.XLOOKUP($D6,城市信息!$B$1:$B$14,城市信息!$A$1:$A$14) -> 009 | M6: =_xlfn.XLOOKUP($D6,城市信息!$B$1:$B$14,城市信息!$C$1:$C$14) -> 叶超 | N6: =_xlfn.XLOOKUP($D6,城市信息!$B$1:$B$14,城市信息!$D$1:$D$14) -> 二线 | O6: =_xlfn.XLOOKUP($D6,城市信息!$B$1:$B$14,城市信息!$E$1:$E$14) -> 9016 | P6: {=_xlfn.XLOOKUP(A6&B6,'[1]2.4自动化报表-8月获客数据-非乱码'!$A:$A&'[1]2.4自动化报表-8月获客数据-非乱码'!$B:$B,'[1]2.4自动化报表-8月获客数据-非乱码'!$C:$H)} -> 672 | Q6: 662 | R6: 643 | S6: 443 | T6: 209 | U6: 692
A7: 44044 | B7: 南部战区-深圳-深圳一组 | C7: 南部战区 | D7: 深圳 | E7: 深圳一组 | F7: 96741 | G7: 8200 | H7: 0 | I7: =_xlfn.XLOOKUP($C7,战区信息!$A$1:$A$5,战区信息!$B$1:$B$5) -> 002 | J7: =_xlfn.XLOOKUP($C7,战区信息!$A$1:$A$5,战区信息!$C$1:$C$5) -> 高安平 | K7: =_xlfn.XLOOKUP($C7,战区信息!$A$1:$A$5,战区信息!$D$1:$D$5) -> 二级战区 | L7: =_xlfn.XLOOKUP($D7,城市信息!$B$1:$B$14,城市信息!$A$1:$A$14) -> 008 | M7: =_xlfn.XLOOKUP($D7,城市信息!$B$1:$B$14,城市信息!$C$1:$C$14) -> 高弘壮 | N7: =_xlfn.XLOOKUP($D7,城市信息!$B$1:$B$14,城市信息!$D$1:$D$14) -> 一线 | O7: =_xlfn.XLOOKUP($D7,城市信息!$B$1:$B$14,城市信息!$E$1:$E$14) -> 11498 | P7: {=_xlfn.XLOOKUP(A7&B7,'[1]2.4自动化报表-8月获客数据-非乱码'!$A:$A&'[1]2.4自动化报表-8月获客数据-非乱码'!$B:$B,'[1]2.4自动化报表-8月获客数据-非乱码'!$C:$H)} -> 3120 | Q7: 3018 | R7: 2877 | S7: 1701 | T7: 900 | U7: 689
A8: 44044 | B8: 南部战区-广州-广州一组 | C8: 南部战区 | D8: 广州 | E8: 广州一组 | F8: 133925 | G8: 10215 | H8: 0 | I8: =_xlfn.XLOOKUP($C8,战区信息!$A$1:$A$5,战区信息!$B$1:$B$5) -> 002 | J8: =_xlfn.XLOOKUP($C8,战区信息!$A$1:$A$5,战区信息!$C$1:$C$5) -> 高安平 | K8: =_xlfn.XLOOKUP($C8,战区信息!$A$1:$A$5,战区信息!$D$1:$D$5) -> 二级战区 | L8: =_xlfn.XLOOKUP($D8,城市信息!$B$1:$B$14,城市信息!$A$1:$A$14) -> 002 | M8: =_xlfn.XLOOKUP($D8,城市信息!$B$1:$B$14,城市信息!$C$1:$C$14) -> 孙乒 | N8: =_xlfn.XLOOKUP($D8,城市信息!$B$1:$B$14,城市信息!$D$1:$D$14) -> 一线 | O8: =_xlfn.XLOOKUP($D8,城市信息!$B$1:$B$14,城市信息!$E$1:$E$14) -> 9854 | P8: {=_xlfn.XLOOKUP(A8&B8,'[1]2.4自动化报表-8月获客数据-非乱码'!$A:$A&'[1]2.4自动化报表-8月获客数据-非乱码'!$B:$B,'[1]2.4自动化报表-8月获客数据-非乱码'!$C:$H)} -> 4721 | Q8: 4611 | R8: 4412 | S8: 2726 | T8: 1527 | U8: 688
A9: 44044 | B9: 南部战区-广州-广州三组 | C9: 南部战区 | D9: 广州 | E9: 广州三组 | F9: 111362 | G9: 9360 | H9: 1110 | I9: =_xlfn.XLOOKUP($C9,战区信息!$A$1:$A$5,战区信息!$B$1:$B$5) -> 002 | J9: =_xlfn.XLOOKUP($C9,战区信息!$A$1:$A$5,战区信息!$C$1:$C$5) -> 高安平 | K9: =_xlfn.XLOOKUP($C9,战区信息!$A$1:$A$5,战区信息!$D$1:$D$5) -> 二级战区 | L9: =_xlfn.XLOOKUP($D9,城市信息!$B$1:$B$14,城市信息!$A$1:$A$14) -> 002 | M9: =_xlfn.XLOOKUP($D9,城市信息!$B$1:$B$14,城市信息!$C$1:$C$14) -> 孙乒 | N9: =_xlfn.XLOOKUP($D9,城市信息!$B$1:$B$14,城市信息!$D$1:$D$14) -> 一线 | O9: =_xlfn.XLOOKUP($D9,城市信息!$B$1:$B$14,城市信息!$E$1:$E$14) -> 9854 | P9: {=_xlfn.XLOOKUP(A9&B9,'[1]2.4自动化报表-8月获客数据-非乱码'!$A:$A&'[1]2.4自动化报表-8月获客数据-非乱码'!$B:$B,'[1]2.4自动化报表-8月获客数据-非乱码'!$C:$H)} -> 3526 | Q9: 3433 | R9: 3267 | S9: 1946 | T9: 1101 | U9: 688
A10: 44044 | B10: 南部战区-广州-广州二组 | C10: 南部战区 | D10: 广州 | E10: 广州二组 | F10: 153104 | G10: 14167 | H10: 10000 | I10: =_xlfn.XLOOKUP($C10,战区信息!$A$1:$A$5,战区信息!$B$1:$B$5) -> 002 | J10: =_xlfn.XLOOKUP($C10,战区信息!$A$1:$A$5,战区信息!$C$1:$C$5) -> 高安平 | K10: =_xlfn.XLOOKUP($C10,战区信息!$A$1:$A$5,战区信息!$D$1:$D$5) -> 二级战区 | L10: =_xlfn.XLOOKUP($D10,城市信息!$B$1:$B$14,城市信息!$A$1:$A$14) -> 002 | M10: =_xlfn.XLOOKUP($D10,城市信息!$B$1:$B$14,城市信息!$C$1:$C$14) -> 孙乒 | N10: =_xlfn.XLOOKUP($D10,城市信息!$B$1:$B$14,城市信息!$D$1:$D$14) -> 一线 | O10: =_xlfn.XLOOKUP($D10,城市信息!$B$1:$B$14,城市信息!$E$1:$E$14) -> 9854 | P10: {=_xlfn.XLOOKUP(A10&B10,'[1]2.4自动化报表-8月获客数据-非乱码'!$A:$A&'[1]2.4自动化报表-8月获客数据-非乱码'!$B:$B,'[1]2.4自动化报表-8月获客数据-非乱码'!$C:$H)} -> 3815 | Q10: 3753 | R10: 3594 | S10: 2217 | T10: 1296 | U10: 690
A11: 44044 | B11: 东部战区-苏州-苏州一组 | C11: 东部战区 | D11: 苏州 | E11: 苏州一组 | F11: 130822 | G11: 11792 | H11: 0 | I11: =_xlfn.XLOOKUP($C11,战区信息!$A$1:$A$5,战区信息!$B$1:$B$5) -> 001 | J11: =_xlfn.XLOOKUP($C11,战区信息!$A$1:$A$5,战区信息!$C$1:$C$5) -> 江永 | K11: =_xlfn.XLOOKUP($C11,战区信息!$A$1:$A$5,战区信息!$D$1:$D$5) -> 一级战区 | L11: =_xlfn.XLOOKUP($D11,城市信息!$B$1:$B$14,城市信息!$A$1:$A$14) -> 013 | M11: =_xlfn.XLOOKUP($D11,城市信息!$B$1:$B$14,城市信息!$C$1:$C$14) -> 张建 | N11: =_xlfn.XLOOKUP($D11,城市信息!$B$1:$B$14,城市信息!$D$1:$D$14) -> 二线 | O11: =_xlfn.XLOOKUP($D11,城市信息!$B$1:$B$14,城市信息!$E$1:$E$14) -> 8800 | P11: {=_xlfn.XLOOKUP(A11&B11,'[1]2.4自动化报表-8月获客数据-非乱码'!$A:$A&'[1]2.4自动化报表-8月获客数据-非乱码'!$B:$B,'[1]2.4自动化报表-8月获客数据-非乱码'!$C:$H)} -> 4758 | Q11: 4593 | R11: 4398 | S11: 2673 | T11: 1352 | U11: 693
A12: 44044 | B12: 东部战区-苏州-苏州三组 | C12: 东部战区 | D12: 苏州 | E12: 苏州三组 | F12: 25305 | G12: 2802 | H12: 758 | I12: =_xlfn.XLOOKUP($C12,战区信息!$A$1:$A$5,战区信息!$B$1:$B$5) -> 001 | J12: =_xlfn.XLOOKUP($C12,战区信息!$A$1:$A$5,战区信息!$C$1:$C$5) -> 江永 | K12: =_xlfn.XLOOKUP($C12,战区信息!$A$1:$A$5,战区信息!$D$1:$D$5) -> 一级战区 | L12: =_xlfn.XLOOKUP($D12,城市信息!$B$1:$B$14,城市信息!$A$1:$A$14) -> 013 | M12: =_xlfn.XLOOKUP($D12,城市信息!$B$1:$B$14,城市信息!$C$1:$C$14) -> 张建 | N12: =_xlfn.XLOOKUP($D12,城市信息!$B$1:$B$14,城市信息!$D$1:$D$14) -> 二线 | O12: =_xlfn.XLOOKUP($D12,城市信息!$B$1:$B$14,城市信息!$E$1:$E$14) -> 8800 | P12: {=_xlfn.XLOOKUP(A12&B12,'[1]2.4自动化报表-8月获客数据-非乱码'!$A:$A&'[1]2.4自动化报表-8月获客数据-非乱码'!$B:$B,'[1]2.4自动化报表-8月获客数据-非乱码'!$C:$H)} -> 361 | Q12: 355 | R12: 325 | S12: 193 | T12: 116 | U12: 691
A13: 44044 | B13: 东部战区-苏州-苏州二组 | C13: 东部战区 | D13: 苏州 | E13: 苏州二组 | F13: 119789 | G13: 12935 | H13: 13080 | I13: =_xlfn.XLOOKUP($C13,战区信息!$A$1:$A$5,战区信息!$B$1:$B$5) -> 001 | J13: =_xlfn.XLOOKUP($C13,战区信息!$A$1:$A$5,战区信息!$C$1:$C$5) -> 江永 | K13: =_xlfn.XLOOKUP($C13,战区信息!$A$1:$A$5,战区信息!$D$1:$D$5) -> 一级战区 | L13: =_xlfn.XLOOKUP($D13,城市信息!$B$1:$B$14,城市信息!$A$1:$A$14) -> 013 | M13: =_xlfn.XLOOKUP($D13,城市信息!$B$1:$B$14,城市信息!$C$1:$C$14) -> 张建 | N13: =_xlfn.XLOOKUP($D13,城市信息!$B$1:$B$14,城市信息!$D$1:$D$14) -> 二线 | O13: =_xlfn.XLOOKUP($D13,城市信息!$B$1:$B$14,城市信息!$E$1:$E$14) -> 8800 | P13: {=_xlfn.XLOOKUP(A13&B13,'[1]2.4自动化报表-8月获客数据-非乱码'!$A:$A&'[1]2.4自动化报表-8月获客数据-非乱码'!$B:$B,'[1]2.4自动化报表-8月获客数据-非乱码'!$C:$H)} -> 4992 | Q13: 4821 | R13: 4607 | S13: 2650 | T13: 1438 | U13: 695
... A867: 44074 | B867: 北部战区-北京-北京二组 | C867: 北部战区 | D867: 北京 | E867: 北京二组 | F867: 9 | G867: 0 | H867: 0 | I867: =_xlfn.XLOOKUP($C867,战区信息!$A$1:$A$5,战区信息!$B$1:$B$5) -> 004 | J867: =_xlfn.XLOOKUP($C867,战区信息!$A$1:$A$5,战区信息!$C$1:$C$5) -> 沈乐欣 | K867: =_xlfn.XLOOKUP($C867,战区信息!$A$1:$A$5,战区信息!$D$1:$D$5) -> 三级战区 | L867: =_xlfn.XLOOKUP($D867,城市信息!$B$1:$B$14,城市信息!$A$1:$A$14) -> 007 | M867: =_xlfn.XLOOKUP($D867,城市信息!$B$1:$B$14,城市信息!$C$1:$C$14) -> 范俊发 | N867: =_xlfn.XLOOKUP($D867,城市信息!$B$1:$B$14,城市信息!$D$1:$D$14) -> 一线 | O867: =_xlfn.XLOOKUP($D867,城市信息!$B$1:$B$14,城市信息!$E$1:$E$14) -> 12358 | P867: {=_xlfn.XLOOKUP(A867&B867,'[1]2.4自动化报表-8月获客数据-非乱码'!$A:$A&'[1]2.4自动化报表-8月获客数据-非乱码'!$B:$B,'[1]2.4自动化报表-8月获客数据-非乱码'!$C:$H)} -> 207 | Q867: 204 | R867: 195 | S867: 121 | T867: 79 | U867: 696

Sheet 战区信息
A1: 战区名称 | B1: 战区编号 | C1: 战区经理 | D1: 战区等级
A2: 东部战区 | B2: 001 | C2: 江永 | D2: 一级战区
A3: 西部战区 | B3: 003 | C3: 田楠 | D3: 二级战区
A4: 南部战区 | B4: 002 | C4: 高安平 | D4: 二级战区
A5: 北部战区 | B5: 004 | C5: 沈乐欣 | D5: 三级战区

Sheet 城市信息
A1: 城市编号 | B1: 城市名称 | C1: 城市经理 | D1: 城市等级 | E1: 平均月薪
A2: 001 | B2: 上海 | C2: 吴刚 | D2: 一线 | E2: 12114
A3: 002 | B3: 广州 | C3: 孙乒 | D3: 一线 | E3: 9854
A4: 003 | B4: 杭州 | C4: 杜光亮 | D4: 二线 | E4: 10499
A5: 004 | B5: 南京 | C5: 苏川 | D5: 二线 | E5: 9912
A6: 005 | B6: 合肥 | C6: 侯阳冰 | D6: 二线 | E6: 8694
A7: 006 | B7: 武汉 | C7: 王刚 | D7: 二线 | E7: 9107
A8: 007 | B8: 北京 | C8: 范俊发 | D8: 一线 | E8: 12358
A9: 008 | B9: 深圳 | C9: 高弘壮 | D9: 一线 | E9: 11498
A10: 009 | B10: 成都 | C10: 叶超 | D10: 二线 | E10: 9016
A11: 010 | B11: 西安 | C11: 黄鹏天 | D11: 二线 | E11: 8295
A12: 011 | B12: 天津 | C12: 冯谦 | D12: 一线 | E12: 8244
A13: 012 | B13: 重庆 | C13: 于子默 | D13: 二线 | E13: 9713
A14: 013 | B14: 苏州 | C14: 张建 | D14: 二线 | E14: 8800

Sheet 自动化报表
A1: 互联网金融-数据分析周报 | S1: 辅助列-日期 | T1: 战区 | U1: 目标
A2: 数据时间 | B2: 44059 | C2: 至 | D2: =B2+6 -> 44065 | S2: 44044 | T2: 总和 | U2: 103000000
A3: 战区 | B3: 总和 | E3: =P7 -> 前台毛利 | G3: =N7 -> 逾期金额 | I3: =H7 -> 成交额 | K3: =I7 -> 成交人数 | M3: ='8月成交数据'!P1 -> 注册人数 | O3: =K7 -> 注册成交率 | S3: =S2+1 -> 44045 | T3: 东部战区 | U3: 65000000
A4: 月目标 | B4: {=_xlfn.IFS(B3=T2,U2,B3="东部战区",U3,B3="西部战区",U4,B3="南部战区",U5,B3="北部战区",U6)} -> 103000000 | C4: =IF($B$3="总和",SUMIFS('8月成交数据'!$F:$F,'8月成交数据'!$A:$A,">="&EOMONTH(A8,-1)+1,'8月成交数据'!$A:$A,"<="&A14),SUMIFS('8月成交数据'!$F:$F,'8月成交数据'!$A:$A,">="&EOMONTH(A8,-1)+1,'8月成交数据'!$A:$A,"<="&A14,'8月成交数据'!$C:$C,$B$3))/B4 -> 0.6139382 | D4: =C4-1 -> -0.3860618 | E4: =P15 -> -53907.15 | G4: =N15 -> 405873 | I4: =H15 -> 22972405 | K4: =E15 -> 334338 | M4: =C15 -> 592742 | O4: =K15 -> 0.30750141 | S4: =S3+1 -> 44046 | T4: 南部战区 | U4: 13000000
A5: 周目标 | B5: =B4/4 -> 25750000 | C5: =H15/B5 -> 0.89213223 | D5: =C5-1 -> -0.10786777 | E5: =P26 -> -80506.63 | F5: =E4/E5-1 -> -0.33040111 | G5: =N26 -> 344488 | H5: =G4/G5-1 -> 0.17819198 | I5: =H26 -> 19314421 | J5: =I4/I5-1 -> 0.18939134 | K5: =I26 -> 175103 | L5: =K4/K5 -> 1.9093791 | M5: =C26 -> 569082 | N5: =M4/M5-1 -> 0.041575731 | O5: =K26 -> 0.30769379 | P5: =O4/O5-1 -> -0.00062525102 | S5: =S4+1 -> 44047 | T5: 北部战区 | U5: 5000000
C6: 流量 | H6: 成交 | L6: 成本 | N6: 风险 | O6: 利润 | S6: =S5+1 -> 44048 | T6: 西部战区 | U6: 20000000
A7: 日期 | B7: 日期 | C7: ='8月成交数据'!P1 -> 注册人数 | D7: ='8月成交数据'!R1 -> 戳额人数 | E7: 给额人数 | F7: 戳额率 | G7: 给额率 | H7: 成交额 | I7: 成交人数 | J7: 给额成交率 | K7: 注册成交率 | L7: 资金成本 | M7: 获客成本 | N7: 逾期金额 | O7: 应收利息 | P7: 前台毛利 | S7: =S6+1 -> 44049
A8: =B2 -> 44059 | B8: =A8 -> 44059 | C8: =IF($B$3="总和",SUMIFS('8月成交数据'!$P:$P,'8月成交数据'!A:A,$A8),SUMIFS('8月成交数据'!$P:$P,'8月成交数据'!$A:$A,$A8,'8月成交数据'!$C:$C,$B$3)) -> 81764 | D8: =IF($B$3="总和",SUMIFS('8月成交数据'!$R:$R,'8月成交数据'!$A:$A,$A8),SUMIFS('8月成交数据'!$R:$R,'8月成交数据'!$A:$A,$A8,'8月成交数据'!$C:$C,$B$3)) -> 76225 | E8: =IF($B$3="总和",SUMIFS('8月成交数据'!$S:$S,'8月成交数据'!$A:$A,$A8),SUMIFS('8月成交数据'!$S:$S,'8月成交数据'!$A:$A,$A8,'8月成交数据'!$C:$C,$B$3)) -> 46042 | F8: =D8/C8 -> 0.93225625 | G8: =E8/D8 -> 0.60402755 | H8: =IF($B$3="总和",SUMIFS('8月成交数据'!$F:$F,'8月成交数据'!$A:$A,$A8),SUMIFS('8月成交数据'!$F:$F,'8月成交数据'!$A:$A,$A8,'8月成交数据'!$C:$C,$B$3)) -> 3370709 | I8: =IF($B$3="总和",SUMIFS('8月成交数据'!$T:$T,'8月成交数据'!$A:$A,$A8),SUMIFS('8月成交数据'!$T:$T,'8月成交数据'!$A:$A,$A8,'8月成交数据'!$C:$C,$B$3)) -> 25466 | J8: =I8/E8 -> 0.55310369 | K8: =I8/C8 -> 0.31145737 | L8: =H8*0.03 -> 101121.27 | M8: =C8*0.5 -> 40882 | N8: =IF($B$3="总和",SUMIFS('8月成交数据'!$H:$H,'8月成交数据'!$A:$A,$A8),SUMIFS('8月成交数据'!$H:$H,'8月成交数据'!$A:$A,$A8,'8月成交数据'!$C:$C,$B$3)) -> 52376 | O8: =IF($B$3="总和",SUMIFS('8月成交数据'!$G:$G,'8月成交数据'!$A:$A,$A8),SUMIFS('8月成交数据'!$G:$G,'8月成交数据'!$A:$A,$A8,'8月成交数据'!$C:$C,$B$3)) -> 222896 | P8: =O8-L8-M8-N8 -> 28516.73 | S8: =S7+1 -> 44050
A9: =A8+1 -> 44060 | B9: =A9 -> 44060 | C9: =IF($B$3="总和",SUMIFS('8月成交数据'!$P:$P,'8月成交数据'!A:A,$A9),SUMIFS('8月成交数据'!$P:$P,'8月成交数据'!$A:$A,$A9,'8月成交数据'!$C:$C,$B$3)) -> 81385 | D9: =IF($B$3="总和",SUMIFS('8月成交数据'!$R:$R,'8月成交数据'!$A:$A,$A9),SUMIFS('8月成交数据'!$R:$R,'8月成交数据'!$A:$A,$A9,'8月成交数据'!$C:$C,$B$3)) -> 75926 | E9: =IF($B$3="总和",SUMIFS('8月成交数据'!$S:$S,'8月成交数据'!$A:$A,$A9),SUMIFS('8月成交数据'!$S:$S,'8月成交数据'!$A:$A,$A9,'8月成交数据'!$C:$C,$B$3)) -> 45914 | F9: =D9/C9 -> 0.93292376 | G9: =E9/D9 -> 0.60472039 | H9: =IF($B$3="总和",SUMIFS('8月成交数据'!$F:$F,'8月成交数据'!$A:$A,$A9),SUMIFS('8月成交数据'!$F:$F,'8月成交数据'!$A:$A,$A9,'8月成交数据'!$C:$C,$B$3)) -> 2979802 | I9: =IF($B$3="总和",SUMIFS('8月成交数据'!$T:$T,'8月成交数据'!$A:$A,$A9),SUMIFS('8月成交数据'!$T:$T,'8月成交数据'!$A:$A,$A9,'8月成交数据'!$C:$C,$B$3)) -> 24945 | J9: =I9/E9 -> 0.54329834 | K9: =I9/C9 -> 0.30650611 | L9: =H9*0.03 -> 89394.06 | M9: =C9*0.5 -> 40692.5 | N9: =IF($B$3="总和",SUMIFS('8月成交数据'!$H:$H,'8月成交数据'!$A:$A,$A9),SUMIFS('8月成交数据'!$H:$H,'8月成交数据'!$A:$A,$A9,'8月成交数据'!$C:$C,$B$3)) -> 25603 | O9: =IF($B$3="总和",SUMIFS('8月成交数据'!$G:$G,'8月成交数据'!$A:$A,$A9),SUMIFS('8月成交数据'!$G:$G,'8月成交数据'!$A:$A,$A9,'8月成交数据'!$C:$C,$B$3)) -> 145812 | P9: =O9-L9-M9-N9 -> -9877.56 | S9: =S8+1 -> 44051
A10: =A9+1 -> 44061 | B10: =A10 -> 44061 | C10: =IF($B$3="总和",SUMIFS('8月成交数据'!$P:$P,'8月成交数据'!A:A,$A10),SUMIFS('8月成交数据'!$P:$P,'8月成交数据'!$A:$A,$A10,'8月成交数据'!$C:$C,$B$3)) -> 73170 | D10: =IF($B$3="总和",SUMIFS('8月成交数据'!$R:$R,'8月成交数据'!$A:$A,$A10),SUMIFS('8月成交数据'!$R:$R,'8月成交数据'!$A:$A,$A10,'8月成交数据'!$C:$C,$B$3)) -> 68234 | E10: =IF($B$3="总和",SUMIFS('8月成交数据'!$S:$S,'8月成交数据'!$A:$A,$A10),SUMIFS('8月成交数据'!$S:$S,'8月成交数据'!$A:$A,$A10,'8月成交数据'!$C:$C,$B$3)) -> 41008 | F10: =D10/C10 -> 0.93254066 | G10: =E10/D10 -> 0.60099071 | H10: =IF($B$3="总和",SUMIFS('8月成交数据'!$F:$F,'8月成交数据'!$A:$A,$A10),SUMIFS('8月成交数据'!$F:$F,'8月成交数据'!$A:$A,$A10,'8月成交数据'!$C:$C,$B$3)) -> 1627270 | I10: =IF($B$3="总和",SUMIFS('8月成交数据'!$T:$T,'8月成交数据'!$A:$A,$A10),SUMIFS('8月成交数据'!$T:$T,'8月成交数据'!$A:$A,$A10,'8月成交数据'!$C:$C,$B$3)) -> 22599 | J10: =I10/E10 -> 0.55108759 | K10: =I10/C10 -> 0.30885609 | L10: =H10*0.03 -> 48818.1 | M10: =C10*0.5 -> 36585 | N10: =IF($B$3="总和",SUMIFS('8月成交数据'!$H:$H,'8月成交数据'!$A:$A,$A10),SUMIFS('8月成交数据'!$H:$H,'8月成交数据'!$A:$A,$A10,'8月成交数据'!$C:$C,$B$3)) -> 17689 | O10: =IF($B$3="总和",SUMIFS('8月成交数据'!$G:$G,'8月成交数据'!$A:$A,$A10),SUMIFS('8月成交数据'!$G:$G,'8月成交数据'!$A:$A,$A10,'8月成交数据'!$C:$C,$B$3)) -> 84108 | P10: =O10-L10-M10-N10 -> -18984.1 | S10: =S9+1 -> 44052
A11: =A10+1 -> 44062 | B11: =A11 -> 44062 | C11: =IF($B$3="总和",SUMIFS('8月成交数据'!$P:$P,'8月成交数据'!A:A,$A11),SUMIFS('8月成交数据'!$P:$P,'8月成交数据'!$A:$A,$A11,'8月成交数据'!$C:$C,$B$3)) -> 87288 | D11: =IF($B$3="总和",SUMIFS('8月成交数据'!$R:$R,'8月成交数据'!$A:$A,$A11),SUMIFS('8月成交数据'!$R:$R,'8月成交数据'!$A:$A,$A11,'8月成交数据'!$C:$C,$B$3)) -> 81476 | E11: =IF($B$3="总和",SUMIFS('8月成交数据'!$S:$S,'8月成交数据'!$A:$A,$A11),SUMIFS('8月成交数据'!$S:$S,'8月成交数据'!$A:$A,$A11,'8月成交数据'!$C:$C,$B$3)) -> 49317 | F11: =D11/C11 -> 0.93341582 | G11: =E11/D11 -> 0.60529481 | H11: =IF($B$3="总和",SUMIFS('8月成交数据'!$F:$F,'8月成交数据'!$A:$A,$A11),SUMIFS('8月成交数据'!$F:$F,'8月成交数据'!$A:$A,$A11,'8月成交数据'!$C:$C,$B$3)) -> 3620618 | I11: =IF($B$3="总和",SUMIFS('8月成交数据'!$T:$T,'8月成交数据'!$A:$A,$A11),SUMIFS('8月成交数据'!$T:$T,'8月成交数据'!$A:$A,$A11,'8月成交数据'!$C:$C,$B$3)) -> 26712 | J11: =I11/E11 -> 0.54163879 | K11: =I11/C11 -> 0.30602145 | L11: =H11*0.03 -> 108618.54 | M11: =C11*0.5 -> 43644 | N11: =IF($B$3="总和",SUMIFS('8月成交数据'!$H:$H,'8月成交数据'!$A:$A,$A11),SUMIFS('8月成交数据'!$H:$H,'8月成交数据'!$A:$A,$A11,'8月成交数据'!$C:$C,$B$3)) -> 92711 | O11: =IF($B$3="总和",SUMIFS('8月成交数据'!$G:$G,'8月成交数据'!$A:$A,$A11),SUMIFS('8月成交数据'!$G:$G,'8月成交数据'!$A:$A,$A11,'8月成交数据'!$C:$C,$B$3)) -> 233100 | P11: =O11-L11-M11-N11 -> -11873.54 | S11: =S10+1 -> 44053
A12: =A11+1 -> 44063 | B12: =A12 -> 44063 | C12: =IF($B$3="总和",SUMIFS('8月成交数据'!$P:$P,'8月成交数据'!A:A,$A12),SUMIFS('8月成交数据'!$P:$P,'8月成交数据'!$A:$A,$A12,'8月成交数据'!$C:$C,$B$3)) -> 88537 | D12: =IF($B$3="总和",SUMIFS('8月成交数据'!$R:$R,'8月成交数据'!$A:$A,$A12),SUMIFS('8月成交数据'!$R:$R,'8月成交数据'!$A:$A,$A12,'8月成交数据'!$C:$C,$B$3)) -> 82589 | E12: =IF($B$3="总和",SUMIFS('8月成交数据'!$S:$S,'8月成交数据'!$A:$A,$A12),SUMIFS('8月成交数据'!$S:$S,'8月成交数据'!$A:$A,$A12,'8月成交数据'!$C:$C,$B$3)) -> 49926 | F12: =D12/C12 -> 0.93281905 | G12: =E12/D12 -> 0.6045115 | H12: =IF($B$3="总和",SUMIFS('8月成交数据'!$F:$F,'8月成交数据'!$A:$A,$A12),SUMIFS('8月成交数据'!$F:$F,'8月成交数据'!$A:$A,$A12,'8月成交数据'!$C:$C,$B$3)) -> 3579879 | I12: =IF($B$3="总和",SUMIFS('8月成交数据'!$T:$T,'8月成交数据'!$A:$A,$A12),SUMIFS('8月成交数据'!$T:$T,'8月成交数据'!$A:$A,$A12,'8月成交数据'!$C:$C,$B$3)) -> 27117 | J12: =I12/E12 -> 0.54314385 | K12: =I12/C12 -> 0.30627873 | L12: =H12*0.03 -> 107396.37 | M12: =C12*0.5 -> 44268.5 | N12: =IF($B$3="总和",SUMIFS('8月成交数据'!$H:$H,'8月成交数据'!$A:$A,$A12),SUMIFS('8月成交数据'!$H:$H,'8月成交数据'!$A:$A,$A12,'8月成交数据'!$C:$C,$B$3)) -> 27541 | O12: =IF($B$3="总和",SUMIFS('8月成交数据'!$G:$G,'8月成交数据'!$A:$A,$A12),SUMIFS('8月成交数据'!$G:$G,'8月成交数据'!$A:$A,$A12,'8月成交数据'!$C:$C,$B$3)) -> 199157 | P12: =O12-L12-M12-N12 -> 19951.13 | S12: =S11+1 -> 44054
A13: =A12+1 -> 44064 | B13: =A13 -> 44064 | C13: =IF($B$3="总和",SUMIFS('8月成交数据'!$P:$P,'8月成交数据'!A:A,$A13),SUMIFS('8月成交数据'!$P:$P,'8月成交数据'!$A:$A,$A13,'8月成交数据'!$C:$C,$B$3)) -> 89999 | D13: =IF($B$3="总和",SUMIFS('8月成交数据'!$R:$R,'8月成交数据'!$A:$A,$A13),SUMIFS('8月成交数据'!$R:$R,'8月成交数据'!$A:$A,$A13,'8月成交数据'!$C:$C,$B$3)) -> 84093 | E13: =IF($B$3="总和",SUMIFS('8月成交数据'!$S:$S,'8月成交数据'!$A:$A,$A13),SUMIFS('8月成交数据'!$S:$S,'8月成交数据'!$A:$A,$A13,'8月成交数据'!$C:$C,$B$3)) -> 50879 | F13: =D13/C13 -> 0.93437705 | G13: =E13/D13 -> 0.60503252 | H13: =IF($B$3="总和",SUMIFS('8月成交数据'!$F:$F,'8月成交数据'!$A:$A,$A13),SUMIFS('8月成交数据'!$F:$F,'8月成交数据'!$A:$A,$A13,'8月成交数据'!$C:$C,$B$3)) -> 4114557 | I13: =IF($B$3="总和",SUMIFS('8月成交数据'!$T:$T,'8月成交数据'!$A:$A,$A13),SUMIFS('8月成交数据'!$T:$T,'8月成交数据'!$A:$A,$A13,'8月成交数据'!$C:$C,$B$3)) -> 27661 | J13: =I13/E13 -> 0.54366241 | K13: =I13/C13 -> 0.30734786 | L13: =H13*0.03 -> 123436.71 | M13: =C13*0.5 -> 44999.5 | N13: =IF($B$3="总和",SUMIFS('8月成交数据'!$H:$H,'8月成交数据'!$A:$A,$A13),SUMIFS('8月成交数据'!$H:$H,'8月成交数据'!$A:$A,$A13,'8月成交数据'!$C:$C,$B$3)) -> 96008 | O13: =IF($B$3="总和",SUMIFS('8月成交数据'!$G:$G,'8月成交数据'!$A:$A,$A13),SUMIFS('8月成交数据'!$G:$G,'8月成交数据'!$A:$A,$A13,'8月成交数据'!$C:$C,$B$3)) -> 219780 | P13: =O13-L13-M13-N13 -> -44664.21 | S13: =S12+1 -> 44055
A14: =A13+1 -> 44065 | B14: =A14 -> 44065 | C14: =IF($B$3="总和",SUMIFS('8月成交数据'!$P:$P,'8月成交数据'!A:A,$A14),SUMIFS('8月成交数据'!$P:$P,'8月成交数据'!$A:$A,$A14,'8月成交数据'!$C:$C,$B$3)) -> 90599 | D14: =IF($B$3="总和",SUMIFS('8月成交数据'!$R:$R,'8月成交数据'!$A:$A,$A14),SUMIFS('8月成交数据'!$R:$R,'8月成交数据'!$A:$A,$A14,'8月成交数据'!$C:$C,$B$3)) -> 84522 | E14: =IF($B$3="总和",SUMIFS('8月成交数据'!$S:$S,'8月成交数据'!$A:$A,$A14),SUMIFS('8月成交数据'!$S:$S,'8月成交数据'!$A:$A,$A14,'8月成交数据'!$C:$C,$B$3)) -> 51252 | F14: =D14/C14 -> 0.9329242 | G14: =E14/D14 -> 0.60637467 | H14: =IF($B$3="总和",SUMIFS('8月成交数据'!$F:$F,'8月成交数据'!$A:$A,$A14),SUMIFS('8月成交数据'!$F:$F,'8月成交数据'!$A:$A,$A14,'8月成交数据'!$C:$C,$B$3)) -> 3679570 | I14: =IF($B$3="总和",SUMIFS('8月成交数据'!$T:$T,'8月成交数据'!$A:$A,$A14),SUMIFS('8月成交数据'!$T:$T,'8月成交数据'!$A:$A,$A14,'8月成交数据'!$C:$C,$B$3)) -> 27769 | J14: =I14/E14 -> 0.541813 | K14: =I14/C14 -> 0.30650449 | L14: =H14*0.03 -> 110387.1 | M14: =C14*0.5 -> 45299.5 | N14: =IF($B$3="总和",SUMIFS('8月成交数据'!$H:$H,'8月成交数据'!$A:$A,$A14),SUMIFS('8月成交数据'!$H:$H,'8月成交数据'!$A:$A,$A14,'8月成交数据'!$C:$C,$B$3)) -> 93945 | O14: =IF($B$3="总和",SUMIFS('8月成交数据'!$G:$G,'8月成交数据'!$A:$A,$A14),SUMIFS('8月成交数据'!$G:$G,'8月成交数据'!$A:$A,$A14,'8月成交数据'!$C:$C,$B$3)) -> 232656 | P14: =O14-L14-M14-N14 -> -16975.6 | S14: =S13+1 -> 44056
A15: 总和 | C15: =SUM(C8:C14) -> 592742 | D15: =SUM(D8:D14) -> 553065 | E15: =SUM(E8:E14) -> 334338 | F15: =D15/C15 -> 0.93306194 | G15: =E15/D15 -> 0.60451846 | H15: =SUM(H8:H14) -> 22972405 | I15: =SUM(I8:I14) -> 182269 | J15: =I15/E15 -> 0.54516388 | K15: =I15/C15 -> 0.30750141 | L15: =SUM(L8:L14) -> 689172.15 | M15: =SUM(M8:M14) -> 296371 | N15: =SUM(N8:N14) -> 405873 | O15: =SUM(O8:O14) -> 1337509 | P15: =SUM(P8:P14) -> -53907.15 | S15: =S14+1 -> 44057
S16: =S15+1 -> 44058
C17: 流量 | H17: 成交 | L17: 成本 | N17: 风险 | O17: 利润 | S17: =S16+1 -> 44059
A18: 日期 | B18: 日期 | C18: =C7 -> 注册人数 | D18: =D7 -> 戳额人数 | E18: 给额人数 | F18: 戳额率 | G18: 给额率 | H18: 成交额 | I18: 成交人数 | J18: 给额成交率 | K18: 注册成交率 | L18: 资金成本 | M18: 获客成本 | N18: 逾期金额 | O18: 应收利息 | P18: 前台毛利 | S18: =S17+1 -> 44060
A19: =A8-7 -> 44052 | B19: =A19 -> 44052 | C19: =IF($B$3="总和",SUMIFS('8月成交数据'!$P:$P,'8月成交数据'!A:A,$A19),SUMIFS('8月成交数据'!$P:$P,'8月成交数据'!$A:$A,$A19,'8月成交数据'!$C:$C,$B$3)) -> 86846 | D19: =IF($B$3="总和",SUMIFS('8月成交数据'!$R:$R,'8月成交数据'!$A:$A,$A19),SUMIFS('8月成交数据'!$R:$R,'8月成交数据'!$A:$A,$A19,'8月成交数据'!$C:$C,$B$3)) -> 81149 | E19: =IF($B$3="总和",SUMIFS('8月成交数据'!$S:$S,'8月成交数据'!$A:$A,$A19),SUMIFS('8月成交数据'!$S:$S,'8月成交数据'!$A:$A,$A19,'8月成交数据'!$C:$C,$B$3)) -> 49024 | F19: =D19/C19 -> 0.93440112 | G19: =E19/D19 -> 0.60412328 | H19: =IF($B$3="总和",SUMIFS('8月成交数据'!$F:$F,'8月成交数据'!$A:$A,$A19),SUMIFS('8月成交数据'!$F:$F,'8月成交数据'!$A:$A,$A19,'8月成交数据'!$C:$C,$B$3)) -> 3217120 | I19: =IF($B$3="总和",SUMIFS('8月成交数据'!$T:$T,'8月成交数据'!$A:$A,$A19),SUMIFS('8月成交数据'!$T:$T,'8月成交数据'!$A:$A,$A19,'8月成交数据'!$C:$C,$B$3)) -> 26583 | J19: =I19/E19 -> 0.54224461 | K19: =I19/C19 -> 0.30609354 | L19: =H19*0.03 -> 96513.6 | M19: =C19*0.5 -> 43423 | N19: =IF($B$3="总和",SUMIFS('8月成交数据'!$H:$H,'8月成交数据'!$A:$A,$A19),SUMIFS('8月成交数据'!$H:$H,'8月成交数据'!$A:$A,$A19,'8月成交数据'!$C:$C,$B$3)) -> 74531 | O19: =IF($B$3="总和",SUMIFS('8月成交数据'!$G:$G,'8月成交数据'!$A:$A,$A19),SUMIFS('8月成交数据'!$G:$G,'8月成交数据'!$A:$A,$A19,'8月成交数据'!$C:$C,$B$3)) -> 177892 | P19: =O19-L19-M19-N19 -> -36575.6 | S19: =S18+1 -> 44061
A20: =A19+1 -> 44053 | B20: =A20 -> 44053 | C20: =IF($B$3="总和",SUMIFS('8月成交数据'!$P:$P,'8月成交数据'!A:A,$A20),SUMIFS('8月成交数据'!$P:$P,'8月成交数据'!$A:$A,$A20,'8月成交数据'!$C:$C,$B$3)) -> 76259 | D20: =IF($B$3="总和",SUMIFS('8月成交数据'!$R:$R,'8月成交数据'!$A:$A,$A20),SUMIFS('8月成交数据'!$R:$R,'8月成交数据'!$A:$A,$A20,'8月成交数据'!$C:$C,$B$3)) -> 71373 | E20: =IF($B$3="总和",SUMIFS('8月成交数据'!$S:$S,'8月成交数据'!$A:$A,$A20),SUMIFS('8月成交数据'!$S:$S,'8月成交数据'!$A:$A,$A20,'8月成交数据'!$C:$C,$B$3)) -> 42997 | F20: =D20/C20 -> 0.93592887 | G20: =E20/D20 -> 0.60242669 | H20: =IF($B$3="总和",SUMIFS('8月成交数据'!$F:$F,'8月成交数据'!$A:$A,$A20),SUMIFS('8月成交数据'!$F:$F,'8月成交数据'!$A:$A,$A20,'8月成交数据'!$C:$C,$B$3)) -> 1641138 | I20: =IF($B$3="总和",SUMIFS('8月成交数据'!$T:$T,'8月成交数据'!$A:$A,$A20),SUMIFS('8月成交数据'!$T:$T,'8月成交数据'!$A:$A,$A20,'8月成交数据'!$C:$C,$B$3)) -> 23540 | J20: =I20/E20 -> 0.54748006 | K20: =I20/C20 -> 0.30868488 | L20: =H20*0.03 -> 49234.14 | M20: =C20*0.5 -> 38129.5 | N20: =IF($B$3="总和",SUMIFS('8月成交数据'!$H:$H,'8月成交数据'!$A:$A,$A20),SUMIFS('8月成交数据'!$H:$H,'8月成交数据'!$A:$A,$A20,'8月成交数据'!$C:$C,$B$3)) -> 41597 | O20: =IF($B$3="总和",SUMIFS('8月成交数据'!$G:$G,'8月成交数据'!$A:$A,$A20),SUMIFS('8月成交数据'!$G:$G,'8月成交数据'!$A:$A,$A20,'8月成交数据'!$C:$C,$B$3)) -> 78943 | P20: =O20-L20-M20-N20 -> -50017.64 | S20: =S19+1 -> 44062
A21: =A20+1 -> 44054 | B21: =A21 -> 44054 | C21: =IF($B$3="总和",SUMIFS('8月成交数据'!$P:$P,'8月成交数据'!A:A,$A21),SUMIFS('8月成交数据'!$P:$P,'8月成交数据'!$A:$A,$A21,'8月成交数据'!$C:$C,$B$3)) -> 69531 | D21: =IF($B$3="总和",SUMIFS('8月成交数据'!$R:$R,'8月成交数据'!$A:$A,$A21),SUMIFS('8月成交数据'!$R:$R,'8月成交数据'!$A:$A,$A21,'8月成交数据'!$C:$C,$B$3)) -> 65167 | E21: =IF($B$3="总和",SUMIFS('8月成交数据'!$S:$S,'8月成交数据'!$A:$A,$A21),SUMIFS('8月成交数据'!$S:$S,'8月成交数据'!$A:$A,$A21,'8月成交数据'!$C:$C,$B$3)) -> 39192 | F21: =D21/C21 -> 0.93723663 | G21: =E21/D21 -> 0.60140869 | H21: =IF($B$3="总和",SUMIFS('8月成交数据'!$F:$F,'8月成交数据'!$A:$A,$A21),SUMIFS('8月成交数据'!$F:$F,'8月成交数据'!$A:$A,$A21,'8月成交数据'!$C:$C,$B$3)) -> 1624037 | I21: =IF($B$3="总和",SUMIFS('8月成交数据'!$T:$T,'8月成交数据'!$A:$A,$A21),SUMIFS('8月成交数据'!$T:$T,'8月成交数据'!$A:$A,$A21,'8月成交数据'!$C:$C,$B$3)) -> 21535 | J21: =I21/E21 -> 0.54947438 | K21: =I21/C21 -> 0.30971797 | L21: =H21*0.03 -> 48721.11 | M21: =C21*0.5 -> 34765.5 | N21: =IF($B$3="总和",SUMIFS('8月成交数据'!$H:$H,'8月成交数据'!$A:$A,$A21),SUMIFS('8月成交数据'!$H:$H,'8月成交数据'!$A:$A,$A21,'8月成交数据'!$C:$C,$B$3)) -> 8974 | O21: =IF($B$3="总和",SUMIFS('8月成交数据'!$G:$G,'8月成交数据'!$A:$A,$A21),SUMIFS('8月成交数据'!$G:$G,'8月成交数据'!$A:$A,$A21,'8月成交数据'!$C:$C,$B$3)) -> 78285 | P21: =O21-L21-M21-N21 -> -14175.61 | S21: =S20+1 -> 44063
A22: =A21+1 -> 44055 | B22: =A22 -> 44055 | C22: =IF($B$3="总和",SUMIFS('8月成交数据'!$P:$P,'8月成交数据'!A:A,$A22),SUMIFS('8月成交数据'!$P:$P,'8月成交数据'!$A:$A,$A22,'8月成交数据'!$C:$C,$B$3)) -> 85105 | D22: =IF($B$3="总和",SUMIFS('8月成交数据'!$R:$R,'8月成交数据'!$A:$A,$A22),SUMIFS('8月成交数据'!$R:$R,'8月成交数据'!$A:$A,$A22,'8月成交数据'!$C:$C,$B$3)) -> 79427 | E22: =IF($B$3="总和",SUMIFS('8月成交数据'!$S:$S,'8月成交数据'!$A:$A,$A22),SUMIFS('8月成交数据'!$S:$S,'8月成交数据'!$A:$A,$A22,'8月成交数据'!$C:$C,$B$3)) -> 48069 | F22: =D22/C22 -> 0.93328242 | G22: =E22/D22 -> 0.60519723 | H22: =IF($B$3="总和",SUMIFS('8月成交数据'!$F:$F,'8月成交数据'!$A:$A,$A22),SUMIFS('8月成交数据'!$F:$F,'8月成交数据'!$A:$A,$A22,'8月成交数据'!$C:$C,$B$3)) -> 2916602 | I22: =IF($B$3="总和",SUMIFS('8月成交数据'!$T:$T,'8月成交数据'!$A:$A,$A22),SUMIFS('8月成交数据'!$T:$T,'8月成交数据'!$A:$A,$A22,'8月成交数据'!$C:$C,$B$3)) -> 25956 | J22: =I22/E22 -> 0.53997379 | K22: =I22/C22 -> 0.30498796 | L22: =H22*0.03 -> 87498.06 | M22: =C22*0.5 -> 42552.5 | N22: =IF($B$3="总和",SUMIFS('8月成交数据'!$H:$H,'8月成交数据'!$A:$A,$A22),SUMIFS('8月成交数据'!$H:$H,'8月成交数据'!$A:$A,$A22,'8月成交数据'!$C:$C,$B$3)) -> 64830 | O22: =IF($B$3="总和",SUMIFS('8月成交数据'!$G:$G,'8月成交数据'!$A:$A,$A22),SUMIFS('8月成交数据'!$G:$G,'8月成交数据'!$A:$A,$A22,'8月成交数据'!$C:$C,$B$3)) -> 145958 | P22: =O22-L22-M22-N22 -> -48922.56 | S22: =S21+1 -> 44064
A23: =A22+1 -> 44056 | B23: =A23 -> 44056 | C23: =IF($B$3="总和",SUMIFS('8月成交数据'!$P:$P,'8月成交数据'!A:A,$A23),SUMIFS('8月成交数据'!$P:$P,'8月成交数据'!$A:$A,$A23,'8月成交数据'!$C:$C,$B$3)) -> 78514 | D23: =IF($B$3="总和",SUMIFS('8月成交数据'!$R:$R,'8月成交数据'!$A:$A,$A23),SUMIFS('8月成交数据'!$R:$R,'8月成交数据'!$A:$A,$A23,'8月成交数据'!$C:$C,$B$3)) -> 73252 | E23: =IF($B$3="总和",SUMIFS('8月成交数据'!$S:$S,'8月成交数据'!$A:$A,$A23),SUMIFS('8月成交数据'!$S:$S,'8月成交数据'!$A:$A,$A23,'8月成交数据'!$C:$C,$B$3)) -> 44164 | F23: =D23/C23 -> 0.93298011 | G23: =E23/D23 -> 0.60290504 | H23: =IF($B$3="总和",SUMIFS('8月成交数据'!$F:$F,'8月成交数据'!$A:$A,$A23),SUMIFS('8月成交数据'!$F:$F,'8月成交数据'!$A:$A,$A23,'8月成交数据'!$C:$C,$B$3)) -> 2801941 | I23: =IF($B$3="总和",SUMIFS('8月成交数据'!$T:$T,'8月成交数据'!$A:$A,$A23),SUMIFS('8月成交数据'!$T:$T,'8月成交数据'!$A:$A,$A23,'8月成交数据'!$C:$C,$B$3)) -> 24133 | J23: =I23/E23 -> 0.54644054 | K23: =I23/C23 -> 0.30737193 | L23: =H23*0.03 -> 84058.23 | M23: =C23*0.5 -> 39257 | N23: =IF($B$3="总和",SUMIFS('8月成交数据'!$H:$H,'8月成交数据'!$A:$A,$A23),SUMIFS('8月成交数据'!$H:$H,'8月成交数据'!$A:$A,$A23,'8月成交数据'!$C:$C,$B$3)) -> 35669 | O23: =IF($B$3="总和",SUMIFS('8月成交数据'!$G:$G,'8月成交数据'!$A:$A,$A23),SUMIFS('8月成交数据'!$G:$G,'8月成交数据'!$A:$A,$A23,'8月成交数据'!$C:$C,$B$3)) -> 143257 | P23: =O23-L23-M23-N23 -> -15727.23 | S23: =S22+1 -> 44065
A24: =A23+1 -> 44057 | B24: =A24 -> 44057 | C24: =IF($B$3="总和",SUMIFS('8月成交数据'!$P:$P,'8月成交数据'!A:A,$A24),SUMIFS('8月成交数据'!$P:$P,'8月成交数据'!$A:$A,$A24,'8月成交数据'!$C:$C,$B$3)) -> 86306 | D24: =IF($B$3="总和",SUMIFS('8月成交数据'!$R:$R,'8月成交数据'!$A:$A,$A24),SUMIFS('8月成交数据'!$R:$R,'8月成交数据'!$A:$A,$A24,'8月成交数据'!$C:$C,$B$3)) -> 80638 | E24: =IF($B$3="总和",SUMIFS('8月成交数据'!$S:$S,'8月成交数据'!$A:$A,$A24),SUMIFS('8月成交数据'!$S:$S,'8月成交数据'!$A:$A,$A24,'8月成交数据'!$C:$C,$B$3)) -> 48927 | F24: =D24/C24 -> 0.9343267 | G24: =E24/D24 -> 0.60674868 | H24: =IF($B$3="总和",SUMIFS('8月成交数据'!$F:$F,'8月成交数据'!$A:$A,$A24),SUMIFS('8月成交数据'!$F:$F,'8月成交数据'!$A:$A,$A24,'8月成交数据'!$C:$C,$B$3)) -> 3641364 | I24: =IF($B$3="总和",SUMIFS('8月成交数据'!$T:$T,'8月成交数据'!$A:$A,$A24),SUMIFS('8月成交数据'!$T:$T,'8月成交数据'!$A:$A,$A24,'8月成交数据'!$C:$C,$B$3)) -> 26744 | J24: =I24/E24 -> 0.54661026 | K24: =I24/C24 -> 0.30987417 | L24: =H24*0.03 -> 109240.92 | M24: =C24*0.5 -> 43153 | N24: =IF($B$3="总和",SUMIFS('8月成交数据'!$H:$H,'8月成交数据'!$A:$A,$A24),SUMIFS('8月成交数据'!$H:$H,'8月成交数据'!$A:$A,$A24,'8月成交数据'!$C:$C,$B$3)) -> 86343 | O24: =IF($B$3="总和",SUMIFS('8月成交数据'!$G:$G,'8月成交数据'!$A:$A,$A24),SUMIFS('8月成交数据'!$G:$G,'8月成交数据'!$A:$A,$A24,'8月成交数据'!$C:$C,$B$3)) -> 191912 | P24: =O24-L24-M24-N24 -> -46824.92 | S24: =S23+1 -> 44066
A25: =A24+1 -> 44058 | B25: =A25 -> 44058 | C25: =IF($B$3="总和",SUMIFS('8月成交数据'!$P:$P,'8月成交数据'!A:A,$A25),SUMIFS('8月成交数据'!$P:$P,'8月成交数据'!$A:$A,$A25,'8月成交数据'!$C:$C,$B$3)) -> 86521 | D25: =IF($B$3="总和",SUMIFS('8月成交数据'!$R:$R,'8月成交数据'!$A:$A,$A25),SUMIFS('8月成交数据'!$R:$R,'8月成交数据'!$A:$A,$A25,'8月成交数据'!$C:$C,$B$3)) -> 80793 | E25: =IF($B$3="总和",SUMIFS('8月成交数据'!$S:$S,'8月成交数据'!$A:$A,$A25),SUMIFS('8月成交数据'!$S:$S,'8月成交数据'!$A:$A,$A25,'8月成交数据'!$C:$C,$B$3)) -> 48812 | F25: =D25/C25 -> 0.93379642 | G25: =E25/D25 -> 0.60416125 | H25: =IF($B$3="总和",SUMIFS('8月成交数据'!$F:$F,'8月成交数据'!$A:$A,$A25),SUMIFS('8月成交数据'!$F:$F,'8月成交数据'!$A:$A,$A25,'8月成交数据'!$C:$C,$B$3)) -> 3472219 | I25: =IF($B$3="总和",SUMIFS('8月成交数据'!$T:$T,'8月成交数据'!$A:$A,$A25),SUMIFS('8月成交数据'!$T:$T,'8月成交数据'!$A:$A,$A25,'8月成交数据'!$C:$C,$B$3)) -> 26612 | J25: =I25/E25 -> 0.5451938 | K25: =I25/C25 -> 0.30757851 | L25: =H25*0.03 -> 104166.57 | M25: =C25*0.5 -> 43260.5 | N25: =IF($B$3="总和",SUMIFS('8月成交数据'!$H:$H,'8月成交数据'!$A:$A,$A25),SUMIFS('8月成交数据'!$H:$H,'8月成交数据'!$A:$A,$A25,'8月成交数据'!$C:$C,$B$3)) -> 32544 | O25: =IF($B$3="总和",SUMIFS('8月成交数据'!$G:$G,'8月成交数据'!$A:$A,$A25),SUMIFS('8月成交数据'!$G:$G,'8月成交数据'!$A:$A,$A25,'8月成交数据'!$C:$C,$B$3)) -> 311708 | P25: =O25-L25-M25-N25 -> 131736.93 | S25: =S24+1 -> 44067
A26: 总和 | C26: =SUM(C19:C25) -> 569082 | D26: =SUM(D19:D25) -> 531799 | E26: =SUM(E19:E25) -> 321185 | F26: =D26/C26 -> 0.93448572 | G26: =E26/D26 -> 0.60395939 | H26: =SUM(H19:H25) -> 19314421 | I26: =SUM(I19:I25) -> 175103 | J26: =I26/E26 -> 0.54517801 | K26: =I26/C26 -> 0.30769379 | L26: =SUM(L19:L25) -> 579432.63 | M26: =SUM(M19:M25) -> 284541 | N26: =SUM(N19:N25) -> 344488 | O26: =SUM(O19:O25) -> 1127955 | P26: =SUM(P19:P25) -> -80506.63 | S26: =S25+1 -> 44068
S27: =S26+1 -> 44069
S28: =S27+1 -> 44070
S29: =S28+1 -> 44071
S30: =S29+1 -> 44072
S31: =S30+1 -> 44073
S32: =S31+1 -> 44074

Sheet 自动化报表 (最终版)
A1: 互联网金融-数据分析周报 | T1: 辅助列-日期 | U1: 战区 | V1: 目标
B2: 数据时间 | C2: 44059 | D2: 至 | E2: =C2+6 -> 44065 | T2: 44044 | U2: 总和 | V2: 103000000
B3: 战区 | C3: 东部战区 | F3: =D7 -> 前台毛利 | H3: =G7 -> 逾期金额 | J3: =F7 -> 成交额 | L3: =J7 -> 成交人数 | N3: ='8月成交数据'!P1 -> 注册人数 | P3: =N7 -> 注册成交率 | T3: =T2+1 -> 44045 | U3: 东部战区 | V3: 65000000
B4: 月目标 | C4: {=_xlfn.IFS(C3=U2,V2,C3="东部战区",V3,C3="西部战区",V4,C3="南部战区",V5,C3="北部战区",V6)} -> 65000000 | D4: =IF($C$3="总和",SUMIFS('8月成交数据'!$F:$F,'8月成交数据'!$A:$A,">="&EOMONTH(B8,-1)+1,'8月成交数据'!$A:$A,"<="&B14),SUMIFS('8月成交数据'!$F:$F,'8月成交数据'!$A:$A,">="&EOMONTH(B8,-1)+1,'8月成交数据'!$A:$A,"<="&B14,'8月成交数据'!$C:$C,$C$3))/C4 -> 0.58182391 | E4: =D4-1 -> -0.41817609 | F4: =D15 -> 28052.16 | H4: =G15 -> 180040 | J4: =F15 -> 13899978 | L4: =K15 -> 197647 | N4: =V15 -> 355321 | P4: =N15 -> 0.29723264 | T4: =T3+1 -> 44046 | U4: 南部战区 | V4: 13000000
B5: 周目标 | C5: =C4/4 -> 16250000 | D5: =F15/C5 -> 0.85538326 | E5: =D5-1 -> -0.14461674 | F5: =D26 -> -15028.86 | G5: =F4/F5-1 -> -2.8665528 | H5: =G26 -> 160001 | I5: =H4/H5-1 -> 0.12524297 | J5: =F26 -> 11147612 | K5: =J4/J5-1 -> 0.24690185 | L5: =J26 -> 101135 | M5: =L4/L5 -> 1.9542888 | N5: =V26 -> 338347 | O5: =N4/N5-1 -> 0.050167432 | P5: =N26 -> 0.29890911 | Q5: =P4/P5-1 -> -0.0056086111 | T5: =T4+1 -> 44047 | U5: 北部战区 | V5: 5000000
B6: 本周 | T6: =T5+1 -> 44048 | U6: 西部战区 | V6: 20000000
B7: 日期 | C7: 星期 | D7: 前台毛利 | E7: 应收利息 | F7: 成交额 | G7: 逾期金额 | H7: 资金成本 | I7: 获客成本 | J7: 成交人数 | K7: 给额人数 | L7: ='8月成交数据'!R1 -> 戳额人数 | M7: 注册人数 | N7: 注册成交率 | O7: 给额成交率 | P7: 给额率 | Q7: 戳额率 | V7: ='8月成交数据'!P1 -> 注册人数
B8: =C2 -> 44059 | C8: =B8 -> 44059 | D8: =E8-H8-I8-G8 -> 5210.32 | E8: =IF($C$3="总和",SUMIFS('8月成交数据'!$G:$G,'8月成交数据'!$A:$A,$B8),SUMIFS('8月成交数据'!$G:$G,'8月成交数据'!$A:$A,$B8,'8月成交数据'!$C:$C,$C$3)) -> 140871 | F8: =IF($C$3="总和",SUMIFS('8月成交数据'!$F:$F,'8月成交数据'!$A:$A,$B8),SUMIFS('8月成交数据'!$F:$F,'8月成交数据'!$A:$A,$B8,'8月成交数据'!$C:$C,$C$3)) -> 2058356 | G8: =IF($C$3="总和",SUMIFS('8月成交数据'!$H:$H,'8月成交数据'!$A:$A,$B8),SUMIFS('8月成交数据'!$H:$H,'8月成交数据'!$A:$A,$B8,'8月成交数据'!$C:$C,$C$3)) -> 49808 | H8: =F8*0.03 -> 61750.68 | I8: =V8*0.5 -> 24102 | J8: =IF($C$3="总和",SUMIFS('8月成交数据'!$T:$T,'8月成交数据'!$A:$A,$B8),SUMIFS('8月成交数据'!$T:$T,'8月成交数据'!$A:$A,$B8,'8月成交数据'!$C:$C,$C$3)) -> 14549 | K8: =IF($C$3="总和",SUMIFS('8月成交数据'!$S:$S,'8月成交数据'!$A:$A,$B8),SUMIFS('8月成交数据'!$S:$S,'8月成交数据'!$A:$A,$B8,'8月成交数据'!$C:$C,$C$3)) -> 26763 | L8: =IF($C$3="总和",SUMIFS('8月成交数据'!$R:$R,'8月成交数据'!$A:$A,$B8),SUMIFS('8月成交数据'!$R:$R,'8月成交数据'!$A:$A,$B8,'8月成交数据'!$C:$C,$C$3)) -> 44676 | M8: =IF($C$3="总和",SUMIFS('8月成交数据'!$P:$P,'8月成交数据'!A:A,$B8),SUMIFS('8月成交数据'!$P:$P,'8月成交数据'!$A:$A,$B8,'8月成交数据'!$C:$C,$C$3)) -> 48204 | N8: =J8/V8 -> 0.30182143 | O8: =J8/K8 -> 0.54362366 | P8: =K8/L8 -> 0.59904647 | Q8: =L8/V8 -> 0.92681105 | V8: =IF($C$3="总和",SUMIFS('8月成交数据'!$P:$P,'8月成交数据'!A:A,$B8),SUMIFS('8月成交数据'!$P:$P,'8月成交数据'!$A:$A,$B8,'8月成交数据'!$C:$C,$C$3)) -> 48204
B9: =B8+1 -> 44060 | C9: =B9 -> 44060 | D9: =E9-H9-I9-G9 -> 7079.9 | E9: =IF($C$3="总和",SUMIFS('8月成交数据'!$G:$G,'8月成交数据'!$A:$A,$B9),SUMIFS('8月成交数据'!$G:$G,'8月成交数据'!$A:$A,$B9,'8月成交数据'!$C:$C,$C$3)) -> 94768 | F9: =IF($C$3="总和",SUMIFS('8月成交数据'!$F:$F,'8月成交数据'!$A:$A,$B9),SUMIFS('8月成交数据'!$F:$F,'8月成交数据'!$A:$A,$B9,'8月成交数据'!$C:$C,$C$3)) -> 1944020 | G9: =IF($C$3="总和",SUMIFS('8月成交数据'!$H:$H,'8月成交数据'!$A:$A,$B9),SUMIFS('8月成交数据'!$H:$H,'8月成交数据'!$A:$A,$B9,'8月成交数据'!$C:$C,$C$3)) -> 3811 | H9: =F9*0.03 -> 58320.6 | I9: =V9*0.5 -> 25556.5 | J9: =IF($C$3="总和",SUMIFS('8月成交数据'!$T:$T,'8月成交数据'!$A:$A,$B9),SUMIFS('8月成交数据'!$T:$T,'8月成交数据'!$A:$A,$B9,'8月成交数据'!$C:$C,$C$3)) -> 15086 | K9: =IF($C$3="总和",SUMIFS('8月成交数据'!$S:$S,'8月成交数据'!$A:$A,$B9),SUMIFS('8月成交数据'!$S:$S,'8月成交数据'!$A:$A,$B9,'8月成交数据'!$C:$C,$C$3)) -> 28423 | L9: =IF($C$3="总和",SUMIFS('8月成交数据'!$R:$R,'8月成交数据'!$A:$A,$B9),SUMIFS('8月成交数据'!$R:$R,'8月成交数据'!$A:$A,$B9,'8月成交数据'!$C:$C,$C$3)) -> 47479 | M9: =IF($C$3="总和",SUMIFS('8月成交数据'!$P:$P,'8月成交数据'!A:A,$B9),SUMIFS('8月成交数据'!$P:$P,'8月成交数据'!$A:$A,$B9,'8月成交数据'!$C:$C,$C$3)) -> 51113 | N9: =J9/V9 -> 0.29514996 | O9: =J9/K9 -> 0.53076734 | P9: =K9/L9 -> 0.59864361 | Q9: =L9/V9 -> 0.92890263 | V9: =IF($C$3="总和",SUMIFS('8月成交数据'!$P:$P,'8月成交数据'!A:A,$B9),SUMIFS('8月成交数据'!$P:$P,'8月成交数据'!$A:$A,$B9,'8月成交数据'!$C:$C,$C$3)) -> 51113
B10: =B9+1 -> 44061 | C10: =B10 -> 44061 | D10: =E10-H10-I10-G10 -> -3908.86 | E10: =IF($C$3="总和",SUMIFS('8月成交数据'!$G:$G,'8月成交数据'!$A:$A,$B10),SUMIFS('8月成交数据'!$G:$G,'8月成交数据'!$A:$A,$B10,'8月成交数据'!$C:$C,$C$3)) -> 55733 | F10: =IF($C$3="总和",SUMIFS('8月成交数据'!$F:$F,'8月成交数据'!$A:$A,$B10),SUMIFS('8月成交数据'!$F:$F,'8月成交数据'!$A:$A,$B10,'8月成交数据'!$C:$C,$C$3)) -> 1093712 | G10: =IF($C$3="总和",SUMIFS('8月成交数据'!$H:$H,'8月成交数据'!$A:$A,$B10),SUMIFS('8月成交数据'!$H:$H,'8月成交数据'!$A:$A,$B10,'8月成交数据'!$C:$C,$C$3)) -> 4004 | H10: =F10*0.03 -> 32811.36 | I10: =V10*0.5 -> 22826.5 | J10: =IF($C$3="总和",SUMIFS('8月成交数据'!$T:$T,'8月成交数据'!$A:$A,$B10),SUMIFS('8月成交数据'!$T:$T,'8月成交数据'!$A:$A,$B10,'8月成交数据'!$C:$C,$C$3)) -> 13633 | K10: =IF($C$3="总和",SUMIFS('8月成交数据'!$S:$S,'8月成交数据'!$A:$A,$B10),SUMIFS('8月成交数据'!$S:$S,'8月成交数据'!$A:$A,$B10,'8月成交数据'!$C:$C,$C$3)) -> 25292 | L10: =IF($C$3="总和",SUMIFS('8月成交数据'!$R:$R,'8月成交数据'!$A:$A,$B10),SUMIFS('8月成交数据'!$R:$R,'8月成交数据'!$A:$A,$B10,'8月成交数据'!$C:$C,$C$3)) -> 42395 | M10: =IF($C$3="总和",SUMIFS('8月成交数据'!$P:$P,'8月成交数据'!A:A,$B10),SUMIFS('8月成交数据'!$P:$P,'8月成交数据'!$A:$A,$B10,'8月成交数据'!$C:$C,$C$3)) -> 45653 | N10: =J10/V10 -> 0.29862222 | O10: =J10/K10 -> 0.5390242 | P10: =K10/L10 -> 0.59657979 | Q10: =L10/V10 -> 0.92863558 | V10: =IF($C$3="总和",SUMIFS('8月成交数据'!$P:$P,'8月成交数据'!A:A,$B10),SUMIFS('8月成交数据'!$P:$P,'8月成交数据'!$A:$A,$B10,'8月成交数据'!$C:$C,$C$3)) -> 45653
B11: =B10+1 -> 44062 | C11: =B11 -> 44062 | D11: =E11-H11-I11-G11 -> 10635.11 | E11: =IF($C$3="总和",SUMIFS('8月成交数据'!$G:$G,'8月成交数据'!$A:$A,$B11),SUMIFS('8月成交数据'!$G:$G,'8月成交数据'!$A:$A,$B11,'8月成交数据'!$C:$C,$C$3)) -> 134876 | F11: =IF($C$3="总和",SUMIFS('8月成交数据'!$F:$F,'8月成交数据'!$A:$A,$B11),SUMIFS('8月成交数据'!$F:$F,'8月成交数据'!$A:$A,$B11,'8月成交数据'!$C:$C,$C$3)) -> 2155313 | G11: =IF($C$3="总和",SUMIFS('8月成交数据'!$H:$H,'8月成交数据'!$A:$A,$B11),SUMIFS('8月成交数据'!$H:$H,'8月成交数据'!$A:$A,$B11,'8月成交数据'!$C:$C,$C$3)) -> 33964 | H11: =F11*0.03 -> 64659.39 | I11: =V11*0.5 -> 25617.5 | J11: =IF($C$3="总和",SUMIFS('8月成交数据'!$T:$T,'8月成交数据'!$A:$A,$B11),SUMIFS('8月成交数据'!$T:$T,'8月成交数据'!$A:$A,$B11,'8月成交数据'!$C:$C,$C$3)) -> 15115 | K11: =IF($C$3="总和",SUMIFS('8月成交数据'!$S:$S,'8月成交数据'!$A:$A,$B11),SUMIFS('8月成交数据'!$S:$S,'8月成交数据'!$A:$A,$B11,'8月成交数据'!$C:$C,$C$3)) -> 28524 | L11: =IF($C$3="总和",SUMIFS('8月成交数据'!$R:$R,'8月成交数据'!$A:$A,$B11),SUMIFS('8月成交数据'!$R:$R,'8月成交数据'!$A:$A,$B11,'8月成交数据'!$C:$C,$C$3)) -> 47565 | M11: =IF($C$3="总和",SUMIFS('8月成交数据'!$P:$P,'8月成交数据'!A:A,$B11),SUMIFS('8月成交数据'!$P:$P,'8月成交数据'!$A:$A,$B11,'8月成交数据'!$C:$C,$C$3)) -> 51235 | N11: =J11/V11 -> 0.29501317 | O11: =J11/K11 -> 0.52990464 | P11: =K11/L11 -> 0.59968464 | Q11: =L11/V11 -> 0.92836928 | V11: =IF($C$3="总和",SUMIFS('8月成交数据'!$P:$P,'8月成交数据'!A:A,$B11),SUMIFS('8月成交数据'!$P:$P,'8月成交数据'!$A:$A,$B11,'8月成交数据'!$C:$C,$C$3)) -> 51235
B12: =B11+1 -> 44063 | C12: =B12 -> 44063 | D12: =E12-H12-I12-G12 -> 19865.97 | E12: =IF($C$3="总和",SUMIFS('8月成交数据'!$G:$G,'8月成交数据'!$A:$A,$B12),SUMIFS('8月成交数据'!$G:$G,'8月成交数据'!$A:$A,$B12,'8月成交数据'!$C:$C,$C$3)) -> 110457 | F12: =IF($C$3="总和",SUMIFS('8月成交数据'!$F:$F,'8月成交数据'!$A:$A,$B12),SUMIFS('8月成交数据'!$F:$F,'8月成交数据'!$A:$A,$B12,'8月成交数据'!$C:$C,$C$3)) -> 2041301 | G12: =IF($C$3="总和",SUMIFS('8月成交数据'!$H:$H,'8月成交数据'!$A:$A,$B12),SUMIFS('8月成交数据'!$H:$H,'8月成交数据'!$A:$A,$B12,'8月成交数据'!$C:$C,$C$3)) -> 3099 | H12: =F12*0.03 -> 61239.03 | I12: =V12*0.5 -> 26253 | J12: =IF($C$3="总和",SUMIFS('8月成交数据'!$T:$T,'8月成交数据'!$A:$A,$B12),SUMIFS('8月成交数据'!$T:$T,'8月成交数据'!$A:$A,$B12,'8月成交数据'!$C:$C,$C$3)) -> 15561 | K12: =IF($C$3="总和",SUMIFS('8月成交数据'!$S:$S,'8月成交数据'!$A:$A,$B12),SUMIFS('8月成交数据'!$S:$S,'8月成交数据'!$A:$A,$B12,'8月成交数据'!$C:$C,$C$3)) -> 29219 | L12: =IF($C$3="总和",SUMIFS('8月成交数据'!$R:$R,'8月成交数据'!$A:$A,$B12),SUMIFS('8月成交数据'!$R:$R,'8月成交数据'!$A:$A,$B12,'8月成交数据'!$C:$C,$C$3)) -> 48717 | M12: =IF($C$3="总和",SUMIFS('8月成交数据'!$P:$P,'8月成交数据'!A:A,$B12),SUMIFS('8月成交数据'!$P:$P,'8月成交数据'!$A:$A,$B12,'8月成交数据'!$C:$C,$C$3)) -> 52506 | N12: =J12/V12 -> 0.29636613 | O12: =J12/K12 -> 0.53256443 | P12: =K12/L12 -> 0.5997701 | Q12: =L12/V12 -> 0.92783682 | V12: =IF($C$3="总和",SUMIFS('8月成交数据'!$P:$P,'8月成交数据'!A:A,$B12),SUMIFS('8月成交数据'!$P:$P,'8月成交数据'!$A:$A,$B12,'8月成交数据'!$C:$C,$C$3)) -> 52506
B13: =B12+1 -> 44064 | C13: =B13 -> 44064 | D13: =E13-H13-I13-G13 -> -3964.33 | E13: =IF($C$3="总和",SUMIFS('8月成交数据'!$G:$G,'8月成交数据'!$A:$A,$B13),SUMIFS('8月成交数据'!$G:$G,'8月成交数据'!$A:$A,$B13,'8月成交数据'!$C:$C,$C$3)) -> 121901 | F13: =IF($C$3="总和",SUMIFS('8月成交数据'!$F:$F,'8月成交数据'!$A:$A,$B13),SUMIFS('8月成交数据'!$F:$F,'8月成交数据'!$A:$A,$B13,'8月成交数据'!$C:$C,$C$3)) -> 2369311 | G13: =IF($C$3="总和",SUMIFS('8月成交数据'!$H:$H,'8月成交数据'!$A:$A,$B13),SUMIFS('8月成交数据'!$H:$H,'8月成交数据'!$A:$A,$B13,'8月成交数据'!$C:$C,$C$3)) -> 28301 | H13: =F13*0.03 -> 71079.33 | I13: =V13*0.5 -> 26485 | J13: =IF($C$3="总和",SUMIFS('8月成交数据'!$T:$T,'8月成交数据'!$A:$A,$B13),SUMIFS('8月成交数据'!$T:$T,'8月成交数据'!$A:$A,$B13,'8月成交数据'!$C:$C,$C$3)) -> 15772 | K13: =IF($C$3="总和",SUMIFS('8月成交数据'!$S:$S,'8月成交数据'!$A:$A,$B13),SUMIFS('8月成交数据'!$S:$S,'8月成交数据'!$A:$A,$B13,'8月成交数据'!$C:$C,$C$3)) -> 29498 | L13: =IF($C$3="总和",SUMIFS('8月成交数据'!$R:$R,'8月成交数据'!$A:$A,$B13),SUMIFS('8月成交数据'!$R:$R,'8月成交数据'!$A:$A,$B13,'8月成交数据'!$C:$C,$C$3)) -> 49254 | M13: =IF($C$3="总和",SUMIFS('8月成交数据'!$P:$P,'8月成交数据'!A:A,$B13),SUMIFS('8月成交数据'!$P:$P,'8月成交数据'!$A:$A,$B13,'8月成交数据'!$C:$C,$C$3)) -> 52970 | N13: =J13/V13 -> 0.29775345 | O13: =J13/K13 -> 0.53468032 | P13: =K13/L13 -> 0.59889552 | Q13: =L13/V13 -> 0.92984708 | V13: =IF($C$3="总和",SUMIFS('8月成交数据'!$P:$P,'8月成交数据'!A:A,$B13),SUMIFS('8月成交数据'!$P:$P,'8月成交数据'!$A:$A,$B13,'8月成交数据'!$C:$C,$C$3)) -> 52970
B14: =B13+1 -> 44065 | C14: =B14 -> 44065 | D14: =E14-H14-I14-G14 -> -6865.95 | E14: =IF($C$3="总和",SUMIFS('8月成交数据'!$G:$G,'8月成交数据'!$A:$A,$B14),SUMIFS('8月成交数据'!$G:$G,'8月成交数据'!$A:$A,$B14,'8月成交数据'!$C:$C,$C$3)) -> 144146 | F14: =IF($C$3="总和",SUMIFS('8月成交数据'!$F:$F,'8月成交数据'!$A:$A,$B14),SUMIFS('8月成交数据'!$F:$F,'8月成交数据'!$A:$A,$B14,'8月成交数据'!$C:$C,$C$3)) -> 2237965 | G14: =IF($C$3="总和",SUMIFS('8月成交数据'!$H:$H,'8月成交数据'!$A:$A,$B14),SUMIFS('8月成交数据'!$H:$H,'8月成交数据'!$A:$A,$B14,'8月成交数据'!$C:$C,$C$3)) -> 57053 | H14: =F14*0.03 -> 67138.95 | I14: =V14*0.5 -> 26820 | J14: =IF($C$3="总和",SUMIFS('8月成交数据'!$T:$T,'8月成交数据'!$A:$A,$B14),SUMIFS('8月成交数据'!$T:$T,'8月成交数据'!$A:$A,$B14,'8月成交数据'!$C:$C,$C$3)) -> 15897 | K14: =IF($C$3="总和",SUMIFS('8月成交数据'!$S:$S,'8月成交数据'!$A:$A,$B14),SUMIFS('8月成交数据'!$S:$S,'8月成交数据'!$A:$A,$B14,'8月成交数据'!$C:$C,$C$3)) -> 29928 | L14: =IF($C$3="总和",SUMIFS('8月成交数据'!$R:$R,'8月成交数据'!$A:$A,$B14),SUMIFS('8月成交数据'!$R:$R,'8月成交数据'!$A:$A,$B14,'8月成交数据'!$C:$C,$C$3)) -> 49785 | M14: =IF($C$3="总和",SUMIFS('8月成交数据'!$P:$P,'8月成交数据'!A:A,$B14),SUMIFS('8月成交数据'!$P:$P,'8月成交数据'!$A:$A,$B14,'8月成交数据'!$C:$C,$C$3)) -> 53640 | N14: =J14/V14 -> 0.29636465 | O14: =J14/K14 -> 0.53117482 | P14: =K14/L14 -> 0.60114492 | Q14: =L14/V14 -> 0.92813199 | V14: =IF($C$3="总和",SUMIFS('8月成交数据'!$P:$P,'8月成交数据'!A:A,$B14),SUMIFS('8月成交数据'!$P:$P,'8月成交数据'!$A:$A,$B14,'8月成交数据'!$C:$C,$C$3)) -> 53640
B15: 总和 | D15: =SUM(D8:D14) -> 28052.16 | E15: =SUM(E8:E14) -> 802752 | F15: =SUM(F8:F14) -> 13899978 | G15: =SUM(G8:G14) -> 180040 | H15: =SUM(H8:H14) -> 416999.34 | I15: =SUM(I8:I14) -> 177660.5 | J15: =SUM(J8:J14) -> 105613 | K15: =SUM(K8:K14) -> 197647 | ... M15: =SUM(M8:M14) -> 355321 | N15: =J15/V15 -> 0.29723264 | O15: =J15/K15 -> 0.53435165 | P15: =K15/L15 -> 0.59916452 | Q15: =L15/V15 -> 0.92837462 | V15: =SUM(V8:V14) -> 355321
B17: 上周 | V17: 流量
B18: 日期 | C18: 日期 | D18: 前台毛利 | E18: 应收利息 | F18: 成交额 | G18: 逾期金额 | H18: 资金成本 | I18: 获客成本 | J18: 成交人数 | K18: 给额人数 | L18: =L7 -> 戳额人数 | M18: =M7 -> 注册人数 | N18: 注册成交率 | O18: 给额成交率 | P18: 给额率 | Q18: 戳额率 | V18: =V7 -> 注册人数
B19: =B8-7 -> 44052 | C19: =B19 -> 44052 | D19: =E19-H19-I19-G19 -> -20522.03 | E19: =IF($C$3="总和",SUMIFS('8月成交数据'!$G:$G,'8月成交数据'!$A:$A,$B19),SUMIFS('8月成交数据'!$G:$G,'8月成交数据'!$A:$A,$B19,'8月成交数据'!$C:$C,$C$3)) -> 97633 | F19: =IF($C$3="总和",SUMIFS('8月成交数据'!$F:$F,'8月成交数据'!$A:$A,$B19),SUMIFS('8月成交数据'!$F:$F,'8月成交数据'!$A:$A,$B19,'8月成交数据'!$C:$C,$C$3)) -> 1808401 | G19: =IF($C$3="总和",SUMIFS('8月成交数据'!$H:$H,'8月成交数据'!$A:$A,$B19),SUMIFS('8月成交数据'!$H:$H,'8月成交数据'!$A:$A,$B19,'8月成交数据'!$C:$C,$C$3)) -> 37555 | H19: =F19*0.03 -> 54252.03 | I19: =V19*0.5 -> 26348 | J19: =IF($C$3="总和",SUMIFS('8月成交数据'!$T:$T,'8月成交数据'!$A:$A,$B19),SUMIFS('8月成交数据'!$T:$T,'8月成交数据'!$A:$A,$B19,'8月成交数据'!$C:$C,$C$3)) -> 15563 | K19: =IF($C$3="总和",SUMIFS('8月成交数据'!$S:$S,'8月成交数据'!$A:$A,$B19),SUMIFS('8月成交数据'!$S:$S,'8月成交数据'!$A:$A,$B19,'8月成交数据'!$C:$C,$C$3)) -> 29382 | L19: =IF($C$3="总和",SUMIFS('8月成交数据'!$R:$R,'8月成交数据'!$A:$A,$B19),SUMIFS('8月成交数据'!$R:$R,'8月成交数据'!$A:$A,$B19,'8月成交数据'!$C:$C,$C$3)) -> 49043 | M19: =IF($C$3="总和",SUMIFS('8月成交数据'!$P:$P,'8月成交数据'!A:A,$B19),SUMIFS('8月成交数据'!$P:$P,'8月成交数据'!$A:$A,$B19,'8月成交数据'!$C:$C,$C$3)) -> 52696 | N19: =J19/V19 -> 0.29533551 | O19: =J19/K19 -> 0.52967803 | P19: =K19/L19 -> 0.59910691 | Q19: =L19/V19 -> 0.93067785 | V19: =IF($C$3="总和",SUMIFS('8月成交数据'!$P:$P,'8月成交数据'!A:A,$B19),SUMIFS('8月成交数据'!$P:$P,'8月成交数据'!$A:$A,$B19,'8月成交数据'!$C:$C,$C$3)) -> 52696
B20: =B19+1 -> 44053 | C20: =B20 -> 44053 | D20: =E20-H20-I20-G20 -> -25266.41 | E20: =IF($C$3="总和",SUMIFS('8月成交数据'!$G:$G,'8月成交数据'!$A:$A,$B20),SUMIFS('8月成交数据'!$G:$G,'8月成交数据'!$A:$A,$B20,'8月成交数据'!$C:$C,$C$3)) -> 41948 | F20: =IF($C$3="总和",SUMIFS('8月成交数据'!$F:$F,'8月成交数据'!$A:$A,$B20),SUMIFS('8月成交数据'!$F:$F,'8月成交数据'!$A:$A,$B20,'8月成交数据'!$C:$C,$C$3)) -> 822347 | G20: =IF($C$3="总和",SUMIFS('8月成交数据'!$H:$H,'8月成交数据'!$A:$A,$B20),SUMIFS('8月成交数据'!$H:$H,'8月成交数据'!$A:$A,$B20,'8月成交数据'!$C:$C,$C$3)) -> 20159 | H20: =F20*0.03 -> 24670.41 | I20: =V20*0.5 -> 22385 | J20: =IF($C$3="总和",SUMIFS('8月成交数据'!$T:$T,'8月成交数据'!$A:$A,$B20),SUMIFS('8月成交数据'!$T:$T,'8月成交数据'!$A:$A,$B20,'8月成交数据'!$C:$C,$C$3)) -> 13494 | K20: =IF($C$3="总和",SUMIFS('8月成交数据'!$S:$S,'8月成交数据'!$A:$A,$B20),SUMIFS('8月成交数据'!$S:$S,'8月成交数据'!$A:$A,$B20,'8月成交数据'!$C:$C,$C$3)) -> 24881 | L20: =IF($C$3="总和",SUMIFS('8月成交数据'!$R:$R,'8月成交数据'!$A:$A,$B20),SUMIFS('8月成交数据'!$R:$R,'8月成交数据'!$A:$A,$B20,'8月成交数据'!$C:$C,$C$3)) -> 41784 | M20: =IF($C$3="总和",SUMIFS('8月成交数据'!$P:$P,'8月成交数据'!A:A,$B20),SUMIFS('8月成交数据'!$P:$P,'8月成交数据'!$A:$A,$B20,'8月成交数据'!$C:$C,$C$3)) -> 44770 | N20: =J20/V20 -> 0.30140719 | O20: =J20/K20 -> 0.54234155 | P20: =K20/L20 -> 0.59546716 | Q20: =L20/V20 -> 0.93330355 | V20: =IF($C$3="总和",SUMIFS('8月成交数据'!$P:$P,'8月成交数据'!A:A,$B20),SUMIFS('8月成交数据'!$P:$P,'8月成交数据'!$A:$A,$B20,'8月成交数据'!$C:$C,$C$3)) -> 44770
B21: =B20+1 -> 44054 | C21: =B21 -> 44054 | D21: =E21-H21-I21-G21 -> -6285.44 | E21: =IF($C$3="总和",SUMIFS('8月成交数据'!$G:$G,'8月成交数据'!$A:$A,$B21),SUMIFS('8月成交数据'!$G:$G,'8月成交数据'!$A:$A,$B21,'8月成交数据'!$C:$C,$C$3)) -> 43160 | F21: =IF($C$3="总和",SUMIFS('8月成交数据'!$F:$F,'8月成交数据'!$A:$A,$B21),SUMIFS('8月成交数据'!$F:$F,'8月成交数据'!$A:$A,$B21,'8月成交数据'!$C:$C,$C$3)) -> 937698 | G21: =IF($C$3="总和",SUMIFS('8月成交数据'!$H:$H,'8月成交数据'!$A:$A,$B21),SUMIFS('8月成交数据'!$H:$H,'8月成交数据'!$A:$A,$B21,'8月成交数据'!$C:$C,$C$3)) -> 1252 | H21: =F21*0.03 -> 28130.94 | I21: =V21*0.5 -> 20062.5 | J21: =IF($C$3="总和",SUMIFS('8月成交数据'!$T:$T,'8月成交数据'!$A:$A,$B21),SUMIFS('8月成交数据'!$T:$T,'8月成交数据'!$A:$A,$B21,'8月成交数据'!$C:$C,$C$3)) -> 12131 | K21: =IF($C$3="总和",SUMIFS('8月成交数据'!$S:$S,'8月成交数据'!$A:$A,$B21),SUMIFS('8月成交数据'!$S:$S,'8月成交数据'!$A:$A,$B21,'8月成交数据'!$C:$C,$C$3)) -> 22382 | L21: =IF($C$3="总和",SUMIFS('8月成交数据'!$R:$R,'8月成交数据'!$A:$A,$B21),SUMIFS('8月成交数据'!$R:$R,'8月成交数据'!$A:$A,$B21,'8月成交数据'!$C:$C,$C$3)) -> 37476 | M21: =IF($C$3="总和",SUMIFS('8月成交数据'!$P:$P,'8月成交数据'!A:A,$B21),SUMIFS('8月成交数据'!$P:$P,'8月成交数据'!$A:$A,$B21,'8月成交数据'!$C:$C,$C$3)) -> 40125 | N21: =J21/V21 -> 0.30233022 | O21: =J21/K21 -> 0.54199803 | P21: =K21/L21 -> 0.59723556 | Q21: =L21/V21 -> 0.93398131 | V21: =IF($C$3="总和",SUMIFS('8月成交数据'!$P:$P,'8月成交数据'!A:A,$B21),SUMIFS('8月成交数据'!$P:$P,'8月成交数据'!$A:$A,$B21,'8月成交数据'!$C:$C,$C$3)) -> 40125
B22: =B21+1 -> 44055 | C22: =B22 -> 44055 | D22: =E22-H22-I22-G22 -> -12853.81 | E22: =IF($C$3="总和",SUMIFS('8月成交数据'!$G:$G,'8月成交数据'!$A:$A,$B22),SUMIFS('8月成交数据'!$G:$G,'8月成交数据'!$A:$A,$B22,'8月成交数据'!$C:$C,$C$3)) -> 92846 | F22: =IF($C$3="总和",SUMIFS('8月成交数据'!$F:$F,'8月成交数据'!$A:$A,$B22),SUMIFS('8月成交数据'!$F:$F,'8月成交数据'!$A:$A,$B22,'8月成交数据'!$C:$C,$C$3)) -> 1880377 | G22: =IF($C$3="总和",SUMIFS('8月成交数据'!$H:$H,'8月成交数据'!$A:$A,$B22),SUMIFS('8月成交数据'!$H:$H,'8月成交数据'!$A:$A,$B22,'8月成交数据'!$C:$C,$C$3)) -> 24439 | H22: =F22*0.03 -> 56411.31 | I22: =V22*0.5 -> 24849.5 | J22: =IF($C$3="总和",SUMIFS('8月成交数据'!$T:$T,'8月成交数据'!$A:$A,$B22),SUMIFS('8月成交数据'!$T:$T,'8月成交数据'!$A:$A,$B22,'8月成交数据'!$C:$C,$C$3)) -> 14638 | K22: =IF($C$3="总和",SUMIFS('8月成交数据'!$S:$S,'8月成交数据'!$A:$A,$B22),SUMIFS('8月成交数据'!$S:$S,'8月成交数据'!$A:$A,$B22,'8月成交数据'!$C:$C,$C$3)) -> 27653 | L22: =IF($C$3="总和",SUMIFS('8月成交数据'!$R:$R,'8月成交数据'!$A:$A,$B22),SUMIFS('8月成交数据'!$R:$R,'8月成交数据'!$A:$A,$B22,'8月成交数据'!$C:$C,$C$3)) -> 46133 | M22: =IF($C$3="总和",SUMIFS('8月成交数据'!$P:$P,'8月成交数据'!A:A,$B22),SUMIFS('8月成交数据'!$P:$P,'8月成交数据'!$A:$A,$B22,'8月成交数据'!$C:$C,$C$3)) -> 49699 | N22: =J22/V22 -> 0.29453309 | O22: =J22/K22 -> 0.52934582 | P22: =K22/L22 -> 0.59941907 | Q22: =L22/V22 -> 0.92824805 | V22: =IF($C$3="总和",SUMIFS('8月成交数据'!$P:$P,'8月成交数据'!A:A,$B22),SUMIFS('8月成交数据'!$P:$P,'8月成交数据'!$A:$A,$B22,'8月成交数据'!$C:$C,$C$3)) -> 49699
B23: =B22+1 -> 44056 | C23: =B23 -> 44056 | D23: =E23-H23-I23-G23 -> 3452.34 | E23: =IF($C$3="总和",SUMIFS('8月成交数据'!$G:$G,'8月成交数据'!$A:$A,$B23),SUMIFS('8月成交数据'!$G:$G,'8月成交数据'!$A:$A,$B23,'8月成交数据'!$C:$C,$C$3)) -> 78998 | F23: =IF($C$3="总和",SUMIFS('8月成交数据'!$F:$F,'8月成交数据'!$A:$A,$B23),SUMIFS('8月成交数据'!$F:$F,'8月成交数据'!$A:$A,$B23,'8月成交数据'!$C:$C,$C$3)) -> 1501422 | G23: =IF($C$3="总和",SUMIFS('8月成交数据'!$H:$H,'8月成交数据'!$A:$A,$B23),SUMIFS('8月成交数据'!$H:$H,'8月成交数据'!$A:$A,$B23,'8月成交数据'!$C:$C,$C$3)) -> 6804 | H23: =F23*0.03 -> 45042.66 | I23: =V23*0.5 -> 23699 | J23: =IF($C$3="总和",SUMIFS('8月成交数据'!$T:$T,'8月成交数据'!$A:$A,$B23),SUMIFS('8月成交数据'!$T:$T,'8月成交数据'!$A:$A,$B23,'8月成交数据'!$C:$C,$C$3)) -> 14260 | K23: =IF($C$3="总和",SUMIFS('8月成交数据'!$S:$S,'8月成交数据'!$A:$A,$B23),SUMIFS('8月成交数据'!$S:$S,'8月成交数据'!$A:$A,$B23,'8月成交数据'!$C:$C,$C$3)) -> 26297 | L23: =IF($C$3="总和",SUMIFS('8月成交数据'!$R:$R,'8月成交数据'!$A:$A,$B23),SUMIFS('8月成交数据'!$R:$R,'8月成交数据'!$A:$A,$B23,'8月成交数据'!$C:$C,$C$3)) -> 44053 | M23: =IF($C$3="总和",SUMIFS('8月成交数据'!$P:$P,'8月成交数据'!A:A,$B23),SUMIFS('8月成交数据'!$P:$P,'8月成交数据'!$A:$A,$B23,'8月成交数据'!$C:$C,$C$3)) -> 47398 | N23: =J23/V23 -> 0.30085658 | O23: =J23/K23 -> 0.54226718 | P23: =K23/L23 -> 0.59694005 | Q23: =L23/V23 -> 0.9294274 | V23: =IF($C$3="总和",SUMIFS('8月成交数据'!$P:$P,'8月成交数据'!A:A,$B23),SUMIFS('8月成交数据'!$P:$P,'8月成交数据'!$A:$A,$B23,'8月成交数据'!$C:$C,$C$3)) -> 47398
B24: =B23+1 -> 44057 | C24: =B24 -> 44057 | D24: =E24-H24-I24-G24 -> -27531.55 | E24: =IF($C$3="总和",SUMIFS('8月成交数据'!$G:$G,'8月成交数据'!$A:$A,$B24),SUMIFS('8月成交数据'!$G:$G,'8月成交数据'!$A:$A,$B24,'8月成交数据'!$C:$C,$C$3)) -> 111981 | F24: =IF($C$3="总和",SUMIFS('8月成交数据'!$F:$F,'8月成交数据'!$A:$A,$B24),SUMIFS('8月成交数据'!$F:$F,'8月成交数据'!$A:$A,$B24,'8月成交数据'!$C:$C,$C$3)) -> 2139185 | G24: =IF($C$3="总和",SUMIFS('8月成交数据'!$H:$H,'8月成交数据'!$A:$A,$B24),SUMIFS('8月成交数据'!$H:$H,'8月成交数据'!$A:$A,$B24,'8月成交数据'!$C:$C,$C$3)) -> 50649 | H24: =F24*0.03 -> 64175.55 | I24: =V24*0.5 -> 24688 | J24: =IF($C$3="总和",SUMIFS('8月成交数据'!$T:$T,'8月成交数据'!$A:$A,$B24),SUMIFS('8月成交数据'!$T:$T,'8月成交数据'!$A:$A,$B24,'8月成交数据'!$C:$C,$C$3)) -> 14843 | K24: =IF($C$3="总和",SUMIFS('8月成交数据'!$S:$S,'8月成交数据'!$A:$A,$B24),SUMIFS('8月成交数据'!$S:$S,'8月成交数据'!$A:$A,$B24,'8月成交数据'!$C:$C,$C$3)) -> 27586 | L24: =IF($C$3="总和",SUMIFS('8月成交数据'!$R:$R,'8月成交数据'!$A:$A,$B24),SUMIFS('8月成交数据'!$R:$R,'8月成交数据'!$A:$A,$B24,'8月成交数据'!$C:$C,$C$3)) -> 45917 | M24: =IF($C$3="总和",SUMIFS('8月成交数据'!$P:$P,'8月成交数据'!A:A,$B24),SUMIFS('8月成交数据'!$P:$P,'8月成交数据'!$A:$A,$B24,'8月成交数据'!$C:$C,$C$3)) -> 49376 | N24: =J24/V24 -> 0.30061163 | O24: =J24/K24 -> 0.53806279 | P24: =K24/L24 -> 0.60077967 | Q24: =L24/V24 -> 0.92994572 | V24: =IF($C$3="总和",SUMIFS('8月成交数据'!$P:$P,'8月成交数据'!A:A,$B24),SUMIFS('8月成交数据'!$P:$P,'8月成交数据'!$A:$A,$B24,'8月成交数据'!$C:$C,$C$3)) -> 49376
B25: =B24+1 -> 44058 | C25: =B25 -> 44058 | D25: =E25-H25-I25-G25 -> 73978.04 | E25: =IF($C$3="总和",SUMIFS('8月成交数据'!$G:$G,'8月成交数据'!$A:$A,$B25),SUMIFS('8月成交数据'!$G:$G,'8月成交数据'!$A:$A,$B25,'8月成交数据'!$C:$C,$C$3)) -> 182008 | F25: =IF($C$3="总和",SUMIFS('8月成交数据'!$F:$F,'8月成交数据'!$A:$A,$B25),SUMIFS('8月成交数据'!$F:$F,'8月成交数据'!$A:$A,$B25,'8月成交数据'!$C:$C,$C$3)) -> 2058182 | G25: =IF($C$3="总和",SUMIFS('8月成交数据'!$H:$H,'8月成交数据'!$A:$A,$B25),SUMIFS('8月成交数据'!$H:$H,'8月成交数据'!$A:$A,$B25,'8月成交数据'!$C:$C,$C$3)) -> 19143 | H25: =F25*0.03 -> 61745.46 | I25: =V25*0.5 -> 27141.5 | J25: =IF($C$3="总和",SUMIFS('8月成交数据'!$T:$T,'8月成交数据'!$A:$A,$B25),SUMIFS('8月成交数据'!$T:$T,'8月成交数据'!$A:$A,$B25,'8月成交数据'!$C:$C,$C$3)) -> 16206 | K25: =IF($C$3="总和",SUMIFS('8月成交数据'!$S:$S,'8月成交数据'!$A:$A,$B25),SUMIFS('8月成交数据'!$S:$S,'8月成交数据'!$A:$A,$B25,'8月成交数据'!$C:$C,$C$3)) -> 30233 | L25: =IF($C$3="总和",SUMIFS('8月成交数据'!$R:$R,'8月成交数据'!$A:$A,$B25),SUMIFS('8月成交数据'!$R:$R,'8月成交数据'!$A:$A,$B25,'8月成交数据'!$C:$C,$C$3)) -> 50470 | M25: =IF($C$3="总和",SUMIFS('8月成交数据'!$P:$P,'8月成交数据'!A:A,$B25),SUMIFS('8月成交数据'!$P:$P,'8月成交数据'!$A:$A,$B25,'8月成交数据'!$C:$C,$C$3)) -> 54283 | N25: =J25/V25 -> 0.29854651 | O25: =J25/K25 -> 0.53603678 | P25: =K25/L25 -> 0.59902913 | Q25: =L25/V25 -> 0.92975701 | V25: =IF($C$3="总和",SUMIFS('8月成交数据'!$P:$P,'8月成交数据'!A:A,$B25),SUMIFS('8月成交数据'!$P:$P,'8月成交数据'!$A:$A,$B25,'8月成交数据'!$C:$C,$C$3)) -> 54283
B26: 总和 | D26: =SUM(D19:D25) -> -15028.86 | E26: =SUM(E19:E25) -> 648574 | F26: =SUM(F19:F25) -> 11147612 | G26: =SUM(G19:G25) -> 160001 | H26: =SUM(H19:H25) -> 334428.36 | I26: =SUM(I19:I25) -> 169173.5 | J26: =SUM(J19:J25) -> 101135 | K26: =SUM(K19:K25) -> 188414 | ... M26: =SUM(M19:M25) -> 338347 | N26: =J26/V26 -> 0.29890911 | O26: =J26/K26 -> 0.53677009 | P26: =K26/L26 -> 0.59837523 | Q26: =L26/V26 -> 0.93063039 | V26: =SUM(V19:V25) -> 338347
T27: =Z46+1 -> 1
T28: =T27+1 -> 2
T29: =T28+1 -> 3
T30: =T29+1 -> 4
T31: =T30+1 -> 5
T32: =T31+1 -> 6
